Workbook

Sheet RM_Purchase_YTD
I1: Legend:
J2: complete
J3: Partial
A5: Date of Receipt | B5: PO Number | C5: SKU Code | D5: SKU Description | E5: In QTY | F5: UOM | G5: Supplier | H5: Van # | I5: DR # | J5: PO # | K5: RR #
D6: PURCHASE
A7: 45810 | C7: AC106 | D7: Packaging Tape 2" | E7: 500 | G7: Synergy | J7: PO-25-00257 | K7: RR-25-00560
C8: AC107 | D8: Packaging Tape 1/2" | E8: 500 | J8: PO-25-00356 | K8: RR-25-00561
A10: 45812 | C10: R001 | D10: HDPE Blue | E10: 4375 | F10: =E10/25 -> 175 | G10: Polyprime | H10: IPXU 3764907 | J10: PO-25-00363 | K10: RR-25-00568
C11: R002 | D11: HDPE Red | E11: =1875+400 -> 2275 | F11: =E11/25 -> 91 | J11: PO-25-00363 | K11: RR-25-00568
C12: R019 | D12: PP Recycle Transparent | E12: 850 | F12: =E12/25 -> 34 | J12: PO-25-00363 | K12: RR-25-00568
A14: 45812 | C14: R001 | D14: HDPE Blue | E14: 3690 | F14: =E14/30 -> 123 | G14: WPJ | H14: DRYU 2647278 | J14: PO-25-00355-1 | K14: RR-25-00567
C15: R002 | D15: HDPE Red | E15: 1950 | F15: =E15/30 -> 65 | J15: PO-25-00355-1 | K15: RR-25-00567
C16: R005 | D16: HDPE White | E16: 9900 | F16: =E16/30 -> 330 | J16: PO-25-00355-1 | K16: RR-25-00567
A18: 45814 | C18: R009 | D18: HDPE Film Virgin | E18: 17500 | F18: =E18/25 -> 700 | G18: JP | H18: MSLU 2122159 | J18: PO-25-00332 | K18: RR-25-00562
A20: 45814 | C20: R018 | D20: PP Film Virgin | E20: 10000 | F20: =E20/25 -> 400 | G20: JP | H20: DRYU 2746455 | J20: PO-25-00335 | K20: RR-25-00565
C21: R009 | D21: HDPE Film Virgin | E21: 7500 | F21: =E21/25 -> 300 | G21: JP | J21: PO-25-00332 | K21: RR-25-00563
A23: 45814 | C23: R012 | D23: LLDPE Virgin | E23: 17500 | F23: =E23/25 -> 700 | G23: JP | H23: DRYU 3079803 | J23: PO-25-00334 | K23: RR-25-00566
A25: 45815 | C25: R009 | D25: HDPE Film Virgin | E25: 17500 | F25: =E25/25 -> 700 | G25: JP | H25: MAOU 2080789 | J25: PO-25-00332 | K25: RR-25-00564
A27: 45817 | C27: AC106 | D27: Packaging Tape 2" | E27: 500 | G27: Synergy | J27: PO-25-00356 | K27: RR-25-00570
C28: AC107 | D28: Packaging Tape 1/2" | E28: 500 | J28: PO-25-00356 | K28: RR-25-00570
A30: 45817 | C30: R008 | D30: HDPE Blow Virgin | E30: 17500 | G30: JP | H30: DRYU 3082469 | J30: PO-25-00342 | K30: RR-25-00571
A32: 45819 | C32: R001 | D32: HDPE Blue | E32: 7230 | G32: JP | H32: IPXU 3989436 | J32: PO-25-00375 | K32: RR-25-00583
C33: R005 | D33: HDPE White | E33: 1290 | J33: PO-25-00375 | K33: RR-25-00583
C34: AC021 | D34: Peanut Jar Cap 50mm (Small) | E34: 93000 | G34: Michael | I34: 5041 | J34: PO-25-00163 | K34: RR-25-00573
C35: AC022 | D35: Peanut Jar Cap 67mm (Medium) | E35: 111200 | I35: 5041 | J35: PO-25-00164 | K35: RR-25-00572
A37: 45819 | C37: R001 | D37: HDPE Blue | E37: 4800 | G37: JP | H37: DRYU 2904416 | J37: PO-25-00375 | K37: RR-25-00583
C38: R005 | D38: HDPE White | E38: 1200 | G38: JP | J38: PO-25-00375 | K38: RR-25-00583
C39: AC022 | D39: Peanut Jar Cap 67mm (Medium) | E39: 125600 | G39: Michael | J39: PO-25-00164/380 | K39: RR-25-00576/RR-25-00595/634 | L39: 1st 41600 | M39: 2nd 48400 | N39: 3rd 35600
C40: COL005 | D40: SB Colorant 116 White | E40: 1000 | G40: JP | J40: PO-25-00304 | K40: RR-25-00584
C41: COL007 | D41: Colorant Black 0025 | E41: 1000 | G41: Jp | J41: PO-25-00304 | K41: RR-25-00584
C42: AC004 | D42: Water Container Faucet | E42: 20000 | G42: Cai | J42: PO-25-00341 | K42: RR-25-00585
A44: 45819 | C44: R016 | D44: PP Yarn Virgin | E44: 17500 | G44: JP | H44: DRYU 3079927 | J44: PO-25-00239/PO-25-00333 | K44: RR-25-00580/RR-25-00581
A46: 45820 | C46: R004 | D46: HDPE Black | E46: =450 -> 450 | G46: MJDT | H46: BL(DRYU 2746305 | J46: PO-25-00165 | K46: RR-25-00600
A48: 45820 | C48: AC022 | D48: Peanut Jar Cap 67mm (Medium) | E48: =148000+800 -> 148800 | G48: Michael | H48: DRYU 2645486 | J48: PO-25-00164 | K48: RR-25-00576
C49: R103 | D49: PET Bottle Pre-Formed 12g (30mm) | E49: 30000 | I49: 5033 | J49: PO-25-00155 | K49: RR-25-00577
C50: AC003 | D50: Container Inner Cap | E50: 61500 | I50: 5033 | J50: PO-25-00122/PO-25-00157 | K50: RR-25-00578/RR-25-00579
C51: AC021 | D51: Peanut Jar Cap 50mm (Small) | E51: 345000 | I51: 5009 | J51: PO-25-00163/380 | K51: RR-25-00598/RR-25-00633 | L51: 1st 301000 | M51: 2nd 44000
A53: 45822 | C53: R001 | D53: HDPE Blue | E53: 1200 | G53: WPJ | H53: DRYU 2152366 | J53: PO-25-00369 | K53: RR-25-00586
C54: R002 | D54: HDPE Red | E54: 1200 | J54: PO-25-00369 | K54: RR-25-00586
C55: R003 | D55: HDPE Green | E55: 900 | J55: PO-25-00369 | K55: RR-25-00586
C56: R004 | D56: HDPE Black | E56: 8040 | J56: PO-25-00369 | K56: RR-25-00586
C57: R005 | D57: HDPE White | E57: 4290 | J57: PO-25-00369 | K57: RR-25-00586
C58: R006 | D58: HDPE Yellow | E58: 600 | J58: PO-25-00369 | K58: RR-25-00586
A60: 45825 | C60: R001 | D60: HDPE Blue | E60: 3875 | G60: Polyprime | H60: SDDU 2020532 | J60: PO-25-00365 | K60: RR-25-00608
C61: R004 | D61: HDPE Black | E61: 12950 | J61: PO-25-00365 | K61: RR-25-00608
A63: 45825 | C63: R004 | D63: HDPE Black | E63: 8550 | G63: MJDT | H63: DRYU2633905 | J63: PO-25-00165 | K63: RR-25-00601
C64: R001 | D64: HDPE Blue | E64: 4770 | G64: JP | J64: PO-25-00375/379/401/406 | K64: RR-25-00604/RR-25-00613/614/624 | L64: 1st 1170 | M64: 2nd 630 | N64: 3rd 1500 | O64: 4th 1470
C65: R005 | D65: HDPE White | E65: 2280 | J65: PO-25-00375 | K65: RR-25-00604
A67: 45825 | C67: R001 | D67: HDPE Blue | E67: 5400 | G67: JP | H67: IPXU 3955020
C68: R002 | D68: HDPE Red | E68: 4800 | J68: PO-25-00375 | K68: RR-25-00612
C69: R006 | D69: HDPE Yellow | E69: 360 | J69: PO-25-00379 | K69: RR-25-00615
C70: R029 | D70: PP Injection Virgin | E70: 2500 | J70: PO-25-00277 | K70: RR-25-00610
C71: AC103 | D71: Plastic Strapping | E71: 107 | J71: PO-25-00358 | K71: RR-25-00611 | L71: 1st 100
A73: 45826 | C73: R008 | D73: HDPE Blow Virgin | E73: 17500 | G73: JP | H73: MSLI 860048 | J73: PO-25-00342 | K73: RR-25-00606
A75: 45826 | C75: R006 | D75: HDPE Yellow | E75: 1440 | G75: JP | H75: IRNU 2027344 | J75: PO-25-00379 | K75: RR-25-00616
C76: COL001 | D76: SB Colorant D6 Blue | E76: 1000 | J76: PO-25-00304 | K76: RR-25-00617
C77: COL002 | D77: SB Colorant D4 Green | E77: 1000 | J77: PO-25-00304 | K77: RR-25-00617
C78: COL003 | D78: SB Colorant D5 Orange | E78: 750 | J78: PO-25-00304 | K78: RR-25-00617 | L78: 1st 25
C79: COL004 | D79: SB Colorant D8 Red | E79: 1000 | J79: PO-25-00304 | K79: RR-25-00617
C80: COL006 | D80: SB Colorant D7 Yellow | E80: 750 | J80: PO-25-00304 | K80: RR-25-00617
C81: AC021 | D81: Peanut Jar Cap 50mm (Small) | E81: 459000 | G81: Michael | J81: PO-25-00380
C82: AC004 | D82: Water Container Faucet | E82: 30000 | G82: Akira | J82: PO-25-00341 | K82: RR-25-00602
A84: 45827 | C84: R001 | D84: HDPE Blue | E84: 4775 | G84: Polyprime | H84: IPXU 3819086 | J84: PO-25-00378 | K84: RR-25-00632
C85: R002 | D85: HDPE Red | E85: 6175 | J85: PO-25-00378 | K85: RR-25-00632
C86: R004 | D86: HDPE Black | E86: 4175 | J86: PO-25-00378 | K86: RR-25-00632
C87: R019 | D87: PP Recycle Transparent | E87: 1200 | J87: PO-25-00378 | K87: RR-25-00632
A89: 45827 | C89: R001 | D89: HDPE Blue | E89: 630 | G89: JP | H89: DRYU 2634054 | J89: PO-25-00406 | K89: RR-25-00625
C90: R002 | D90: HDPE Red | E90: 1770 | J90: PO-25-00379 | K90: RR-25-00626
C91: R005 | D91: HDPE White | E91: 9570 | J91: PO-25-00406/PO-25-00379 | K91: RR-25-00625 | L91: 1st 810 | M91: 2nd 3600
C92: R032 | D92: HDPE Injection | E92: 2500
C93: R103 | D93: PET Bottle Pre-Formed 12g (30mm) | E93: 25000 | G93: Michael | J93: PO-25-00155
A95: 45827 | C95: AC101 | D95: Plastic Twine | E95: 1000 | G95: BL | J95: PO-25-00396 | K95: RR-25-00628
A97: 45828 | C97: AC107 | D97: Packaging Tape 1/2" | E97: 500 | G97: synergy | J97: PO-25-00397 | K97: RR-25-00631

Sheet RM_InboundProd_YTD
A5: Date of Receipt | B5: SKU Code | C5: SKU Description | D5: In QTY | E5: UOM | F5: Inbound Document | G5: Location/Area | H5: Received in the Whse by | I5: Remarks
C6: PELLETIZER
A7: 45808 | B7: R003 | C7: HDPE Green | D7: 300 | F7: encoded
B8: R004 | C8: HDPE Black | D8: =25+25 -> 50 | F8: encoded
B9: R006 | C9: HDPE Yellow | D9: =675 -> 675 | F9: encoded
B10: R007 | C10: HDPE Orange | D10: 575 | F10: encoded
B11: R001 | C11: HDPE Blue | D11: 475 | F11: encoded
B12: R005 | C12: HDPE White | D12: 625 | F12: encoded
A14: 45810 | B14: R004 | C14: HDPE Black | D14: =700+325 -> 1025 | F14: encoded
B15: R007 | C15: HDPE Orange | D15: =725 -> 725 | F15: encoded
B16: R003 | C16: HDPE Green | D16: 300 | F16: encoded
B17: R005 | C17: HDPE White | D17: 275 | F17: encoded
A19: 45811 | B19: R004 | C19: HDPE Black | D19: =1925+75 -> 2000 | F19: encoded
B20: R002 | C20: HDPE Red | D20: 325 | F20: encoded
B21: R001 | C21: HDPE Blue | D21: 175 | F21: encoded
B22: R005 | C22: HDPE White | D22: 150 | F22: encoded
A24: 45812 | B24: R003 | C24: HDPE Green | D24: 225 | F24: encoded
B25: R004 | C25: HDPE Black | D25: 1400 | F25: encoded
B26: R007 | C26: HDPE Orange | D26: 200 | F26: encoded
B27: R001 | C27: HDPE Blue | D27: 150 | F27: encoded
B28: R002 | C28: HDPE Red | D28: 175 | F28: encoded
B29: R006 | C29: HDPE Yellow | D29: 350 | F29: encoded
A31: 45813 | B31: R004 | C31: HDPE Black | D31: 1050 | F31: encoded
B32: R002 | C32: HDPE Red | D32: 550 | F32: encoded
B33: R001 | C33: HDPE Blue | D33: 300 | F33: encoded
B34: R003 | C34: HDPE Green | D34: 350 | F34: encoded
B35: R006 | C35: HDPE Yellow | D35: 125 | F35: encoded
B36: R021 | C36: HDV Blue | D36: 275 | F36: encoded
A38: 45814 | B38: R026 | C38: HDV Transparent | D38: 375 | F38: encoded
B39: R027 | C39: HDV White | D39: 750 | F39: encoded
B40: R004 | C40: HDPE Black | D40: 75 | F40: encoded
B41: R001 | C41: HDPE Blue | D41: 400 | F41: encoded
B42: R002 | C42: HDPE Red | D42: 350 | F42: encoded
B43: R005 | C43: HDPE White | D43: 225 | F43: encoded
B44: R025 | C44: HDV Red | D44: 150 | F44: encoded
A46: 45815 | B46: R001 | C46: HDPE Blue | D46: =325+200 -> 525 | F46: encoded
B47: R003 | C47: HDPE Green | D47: =525+150 -> 675 | F47: encoded
B48: R004 | C48: HDPE Black | D48: =25+50 -> 75 | F48: encoded
B49: R005 | C49: HDPE White | D49: 375 | F49: encoded
B50: R021 | C50: HDV Blue | D50: 325 | F50: encoded
B51: R002 | C51: HDPE Red | D51: 75 | F51: encoded
A53: 45817 | B53: R027 | C53: HDV White | D53: =675+250 -> 925 | F53: encoded
B54: R005 | C54: HDPE White | D54: =425+325 -> 750 | F54: encoded
B55: R004 | C55: HDPE Black | D55: =50+25 -> 75 | F55: encoded
B56: R003 | C56: HDPE Green | D56: 250 | F56: encoded
A58: 45818 | B58: R003 | C58: HDPE Green | D58: 125 | F58: encoded
B59: R021 | C59: HDV Blue | D59: 150 | F59: encoded
B60: R002 | C60: HDPE Red | D60: 150 | F60: encoded
B61: R026 | C61: HDV Transparent | D61: =75+275 -> 350 | F61: encoded
B62: R005 | C62: HDPE White | D62: =550+175 -> 725 | F62: encoded
B63: R004 | C63: HDPE Black | D63: =200+300 -> 500 | F63: encoded
B64: R001 | C64: HDPE Blue | D64: 300 | F64: encoded
B65: R007 | C65: HDPE Orange | D65: 200 | F65: encoded
A67: 45819 | B67: R002 | C67: HDPE Red | D67: 450 | F67: encoded
B68: R003 | C68: HDPE Green | D68: 450 | F68: encoded
B69: R026 | C69: HDV Transparent | D69: 100 | F69: encoded
B70: R027 | C70: HDV White | D70: 450 | F70: encoded
B71: R004 | C71: HDPE Black | D71: =75+75 -> 150 | F71: encoded
B72: R006 | C72: HDPE Yellow | D72: 100 | F72: encoded
A74: 45820 | B74: R001 | C74: HDPE Blue | D74: =275+725 -> 1000 | F74: encoded
B75: R006 | C75: HDPE Yellow | D75: 100 | F75: encoded
B76: R023 | C76: HDV Orange | D76: 100 | F76: encoded
B77: R026 | C77: HDV Transparent | D77: 575 | F77: encoded
B78: R004 | C78: HDPE Black | D78: =100+125 -> 225 | F78: encoded
B79: R003 | C79: HDPE Green | D79: 175 | F79: encoded
B80: R002 | C80: HDPE Red | D80: 200 | F80: encoded
B81: R005 | C81: HDPE White | D81: 100 | F81: encoded
A83: 45821 | B83: R021 | C83: HDV Blue | D83: 125 | F83: encoded
B84: R025 | C84: HDV Red | D84: 125 | F84: encoded
B85: R027 | C85: HDV White | D85: =550+300 -> 850 | F85: encoded
B86: R028 | C86: HDV Yellow | D86: 150 | F86: encoded
B87: R004 | C87: HDPE Black | D87: 75 | F87: encoded
B88: R026 | C88: HDV Transparent | D88: 575 | F88: encoded
A90: 45822 | B90: R021 | C90: HDV Blue | D90: 675 | F90: encoded
B91: R026 | C91: HDV Transparent | D91: =1175 -> 1175 | F91: encoded
A93: 45824 | B93: R026 | C93: HDV Transparent | D93: =575+850 -> 1425 | F93: encoded
B94: R027 | C94: HDV White | D94: 425 | F94: encoded
B95: R004 | C95: HDPE Black | D95: =25+75 -> 100 | F95: encoded
A97: 45825 | B97: R026 | C97: HDV Transparent | D97: 1350 | F97: encoded
B98: R027 | C98: HDV White | D98: 625 | F98: encoded
A100: 45827 | B100: R002 | C100: HDPE Red | D100: =1775 -> 1775 | F100: encoded
B101: R001 | C101: HDPE Blue | D101: 350 | F101: encoded
B102: R004 | C102: HDPE Black | D102: 25 | F102: encoded
A104: 45828 | B104: R001 | C104: HDPE Blue | D104: =2325 -> 2325 | F104: encoded
A106: 45829 | B106: R001 | C106: HDPE Blue | D106: =1225 -> 1225 | F106: encoded
B107: R002 | C107: HDPE Red | D107: 1000 | F107: encoded
C113: INJECTION
A114: 45808 | B114: AC002 | C114: Container Outer Cap w/inner lock (RGMC) | D114: =6000+6000 -> 12000 | F114: encoded
A116: 45810 | B116: AC002 | C116: Container Outer Cap w/inner lock (RGMC) | D116: =5000+5000 -> 10000 | F116: encoded
A118: 45811 | B118: AC002 | C118: Container Outer Cap w/inner lock (RGMC) | D118: =4500+6000 -> 10500 | F118: encoded
A120: 45812 | B120: AC002 | C120: Container Outer Cap w/inner lock (RGMC) | D120: =4500+6000 -> 10500 | F120: encoded
A122: 45813 | B122: AC002 | C122: Container Outer Cap w/inner lock (RGMC) | D122: =6000 -> 6000 | F122: encoded
A124: 45814 | B124: AC002 | C124: Container Outer Cap w/inner lock (RGMC) | D124: 6000 | F124: encoded
A126: 45815 | B126: AC002 | C126: Container Outer Cap w/inner lock (RGMC) | D126: =4500+5000 -> 9500 | F126: encoded
A128: 45817 | B128: AC002 | C128: Container Outer Cap w/inner lock (RGMC) | D128: =6000+5500 -> 11500 | F128: encoded
A130: 45818 | B130: AC002 | C130: Container Outer Cap w/inner lock (RGMC) | D130: =6000+6000 -> 12000 | F130: encoded
A132: 45819 | B132: AC002 | C132: Container Outer Cap w/inner lock (RGMC) | D132: =5000+5500 -> 10500 | F132: encoded
A134: 45820 | B134: AC002 | C134: Container Outer Cap w/inner lock (RGMC) | D134: =5500+5000 -> 10500 | F134: encoded
A136: 45821 | B136: AC002 | C136: Container Outer Cap w/inner lock (RGMC) | D136: =6000+6000 -> 12000 | F136: encoded
A138: 45822 | B138: AC002 | C138: Container Outer Cap w/inner lock (RGMC) | D138: =5000+3000 -> 8000 | F138: encoded
...

Sheet RM_Outbound_YTD
K1: Copy formula
C2: Rivson Goldplast Manufacturing Corp
C3: Raw Materials Requisition Logsheet
S4: Test of Reasonableness
A5: Date of request | B5: SKU Code | C5: SKU Description | D5: In QTY | E5: Shift | F5: Process ID | G5: Location/Area | H5: Machine No. | I5: Inter-warehouse transfer required | J5: Department | K5: Requestor | L5: Finished Goods Inventory QTY | M5: Date of processing | N5: Out QTY | O5: Remaining RM inventory QTY | P5: Work In Progress QTY | Q5: Damaged QTY | R5: Damaged Supporting Document | S5: DM Requirement QTY | T5: Should be Finished Goods Output QTY | U5: Variance QTY | V5: Remarks
C6: CB/WC
A7: 45808 | B7: R004 | C7: HDPE Black | D7: =2550 -> 2550 | E7: encoded
B8: AC002 | C8: Container Outer Cap w/inner lock (RGMC) | D8: 2000 | E8: encoded
A10: 45809 | B10: R004 | C10: HDPE Black | D10: =2910 -> 2910 | E10: encoded
B11: AC002 | C11: Container Outer Cap w/inner lock (RGMC) | D11: 2000 | E11: encoded
B12: AC004 | C12: Water Container Faucet | D12: 1000 | E12: encoded
B13: AC006 | C13: Water Container Big Outer Cap w/inner cap (RGMC) | D13: 400 | E13: encoded
B14: R008 | C14: HDPE Blow Virgin | D14: =375+425 -> 800 | E14: encoded
A16: 45810 | B16: R004 | C16: HDPE Black | D16: =1200+225 -> 1425 | E16: encoded
B17: R008 | C17: HDPE Blow Virgin | D17: 175 | E17: encoded
B18: AC006 | C18: Water Container Big Outer Cap w/inner cap (RGMC) | D18: =400+400 -> 800 | E18: encoded
B19: COL007 | C19: Colorant Black 0025 | D19: 6 | E19: encoded
B20: AC002 | C20: Container Outer Cap w/inner lock (RGMC) | D20: =1000+2000 -> 3000 | E20: encoded
C21: HDPE Black | D21: 683
A23: 45811 | B23: R004 | C23: HDPE Black | D23: 450 | E23: encoded
B24: R009 | C24: HDPE Film Virgin | D24: 700 | E24: encoded
B25: R006 | C25: HDPE Yellow | D25: =2100 -> 2100 | E25: encoded
B26: AC002 | C26: Container Outer Cap w/inner lock (RGMC) | D26: 1000 | E26: encoded
B27: COL007 | C27: Colorant Black 0025 | D27: =10+10+10 -> 30 | E27: encoded
A29: 45812 | B29: R004 | C29: HDPE Black | D29: =950 -> 950 | E29: encoded
B30: R006 | C30: HDPE Yellow | D30: =900+300 -> 1200 | E30: encoded
B31: R001 | C31: HDPE Blue | D31: 375
C32: HDPE Yellow | D32: 625
C33: HDPE Blue | D33: =125+125 -> 250
B34: AC002 | C34: Container Outer Cap w/inner lock (RGMC) | D34: =1500+2000+1000 -> 4500 | E34: encoded
A36: 45813 | B36: R004 | C36: HDPE Black | D36: 1475 | E36: encoded
B37: R001 | C37: HDPE Blue | D37: 1250 | E37: encoded
B38: AC002 | C38: Container Outer Cap w/inner lock (RGMC) | D38: =1000+1000+1000 -> 3000 | E38: encoded
B39: AC101 | C39: Plastic Twine | D39: 20 | E39: encoded
A41: 45814 | B41: R001 | C41: HDPE Blue | D41: 1250 | E41: encoded
B42: AC002 | C42: Container Outer Cap w/inner lock (RGMC) | D42: 3000 | E42: encoded
B43: AC101 | C43: Plastic Twine | D43: =40 -> 40 | E43: encoded
A45: 45817 | B45: R006 | C45: HDPE Yellow | D45: =1650 -> 1650 | E45: encoded
B46: R001 | C46: HDPE Blue | D46: =975+325 -> 1300 | E46: encoded
B47: R004 | C47: HDPE Black | D47: 625 | E47: encoded
C48: HDPE Black | D48: 240 | E48: encoded
B49: COL007 | C49: Colorant Black 0025 | D49: 10 | E49: encoded
B50: AC002 | C50: Container Outer Cap w/inner lock (RGMC) | D50: =1000+1500 -> 2500 | E50: encoded
B51: AC101 | C51: Plastic Twine | D51: 20 | E51: encoded
B52: R008 | C52: HDPE Blow Virgin | D52: 675 | E52: encoded
A54: 45818 | B54: R008 | C54: HDPE Blow Virgin | D54: =750+750 -> 1500 | E54: encoded
B55: R002 | C55: HDPE Red | D55: =1150 -> 1150 | E55: encoded
B56: COL007 | C56: Colorant Black 0025 | D56: 20 | E56: encoded
B57: AC002 | C57: Container Outer Cap w/inner lock (RGMC) | D57: =1500+1500+500 -> 3500 | E57: encoded
B58: AC004 | C58: Water Container Faucet | D58: 2000 | E58: encoded
B59: AC005 | C59: Water Container Small Outer Cap | D59: 1500 | E59: encoded
B60: AC006 | C60: Water Container Big Outer Cap w/inner cap (RGMC) | D60: 1000 | E60: encoded
B61: AC101 | C61: Plastic Twine | D61: 40 | E61: encoded
B62: R005 | C62: HDPE White | D62: =450+600 -> 1050 | E62: encoded
B63: R004 | C63: HDPE Black | D63: 75 | E63: encoded
B64: R006 | C64: HDPE Yellow | D64: 900 | E64: encoded
A66: 45819 | B66: R008 | C66: HDPE Blow Virgin | D66: =750+750 -> 1500
B67: R005 | C67: HDPE White | D67: 1110
B68: R001 | C68: HDPE Blue | D68: 600
B69: R004 | C69: HDPE Black | D69: 325
B70: R006 | C70: HDPE Yellow | D70: 690
B71: COL006 | C71: SB Colorant D7 Yellow | D71: 5
B72: COL007 | C72: Colorant Black 0025 | D72: 10
B73: AC101 | C73: Plastic Twine | D73: =20+10 -> 30
B74: AC002 | C74: Container Outer Cap w/inner lock (RGMC) | D74: 1000
B75: AC004 | C75: Water Container Faucet | D75: 2000
B76: AC005 | C76: Water Container Small Outer Cap | D76: 3000
B77: AC006 | C77: Water Container Big Outer Cap w/inner cap (RGMC) | D77: 1400
A79: 45820 | B79: R008 | C79: HDPE Blow Virgin | D79: =750+750 -> 1500
B80: R001 | C80: HDPE Blue | D80: =1800+100 -> 1900
B81: AC002 | C81: Container Outer Cap w/inner lock (RGMC) | D81: =1000+500+1500 -> 3000
B82: COL007 | C82: Colorant Black 0025 | D82: 10
B83: R004 | C83: HDPE Black | D83: =350+450+615 -> 1415
C84: HDPE Black | D84: =150+420 -> 570
B85: AC006 | C85: Water Container Big Outer Cap w/inner cap (RGMC) | D85: 1400
B86: R005 | C86: HDPE White | D86: 55
B87: R006 | C87: HDPE Yellow | D87: 100
B88: AC004 | C88: Water Container Faucet | D88: 1000
B89: AC005 | C89: Water Container Small Outer Cap | D89: 1500
B90: AC101 | C90: Plastic Twine | D90: 20
A92: 45821 | B92: R008 | C92: HDPE Blow Virgin | D92: =750+500 -> 1250
B93: AC002 | C93: Container Outer Cap w/inner lock (RGMC) | D93: 2000
B94: R001 | C94: HDPE Blue | D94: =2400 -> 2400
C95: HDPE Black | D95: 230
B96: AC006 | C96: Water Container Big Outer Cap w/inner cap (RGMC) | D96: 2200
B97: AC004 | C97: Water Container Faucet | D97: =1000+1000 -> 2000
B98: AC101 | C98: Plastic Twine | D98: 40
B99: AC005 | C99: Water Container Small Outer Cap | D99: 1500
A101: 45822 | B101: R001 | C101: HDPE Blue | D101: =1800+600 -> 2400
B102: R004 | C102: HDPE Black | D102: =600+75+150 -> 825
B103: AC002 | C103: Container Outer Cap w/inner lock (RGMC) | D103: 2000
B104: AC006 | C104: Water Container Big Outer Cap w/inner cap (RGMC) | D104: 1800
B105: AC004 | C105: Water Container Faucet | D105: 2000
B106: AC101 | C106: Plastic Twine | D106: =40+10 -> 50
B107: AC005 | C107: Water Container Small Outer Cap | D107: 1500
B108: R008 | C108: HDPE Blow Virgin | D108: =375+625 -> 1000
A110: 45824 | B110: R008 | C110: HDPE Blow Virgin | D110: =500+375+750 -> 1625
B111: R004 | C111: HDPE Black | D111: =3150 -> 3150
B112: AC004 | C112: Water Container Faucet | D112: 2000
B113: AC002 | C113: Container Outer Cap w/inner lock (RGMC) | D113: =1000+2000 -> 3000
...

Sheet RM Rollforward
B1: Rivson Goldplast Manufacturing Corp
B2: Raw Materials Rollforward
B3: As of June 20, 2025
D5: A | E5: B | F5: C | G5: D | H5: E = A + B + C - D
A6: SKU Code | B6: SKU Description | C6: UOM | D6: Beg.Inv | E6: Purchase | F6: Inbound Prod | G6: Outbound | H6: Ending Inventory | J6: Price | L6: Peso Value | M6: Remarks
A7: R001 | B7: HDPE Blue | C7: kg | D7: 675 | E7: =SUMIF(RM_Purchase_YTD!C:C,'RM Rollforward'!A7,RM_Purchase_YTD!E:E) -> 40745 | F7: =SUMIF(RM_InboundProd_YTD!B:B,'RM Rollforward'!A7,RM_InboundProd_YTD!D:D) -> 7225 | G7: =SUMIF(RM_Outbound_YTD!B:B,'RM Rollforward'!A7,RM_Outbound_YTD!D:D) -> 42055 | H7: =D7+E7+F7-G7 -> 6590 | I7: =H7/25 -> 263.6 | J7: 45 | K7: 1 | L7: =H7*J7*K7 -> 296550
A8: R002 | B8: HDPE Red | C8: kg | D8: 250 | E8: =SUMIF(RM_Purchase_YTD!C:C,'RM Rollforward'!A8,RM_Purchase_YTD!E:E) -> 18170 | F8: =SUMIF(RM_InboundProd_YTD!B:B,'RM Rollforward'!A8,RM_InboundProd_YTD!D:D) -> 5050 | G8: =SUMIF(RM_Outbound_YTD!B:B,'RM Rollforward'!A8,RM_Outbound_YTD!D:D) -> 20470 | H8: =D8+E8+F8-G8 -> 3000 | I8: =H8/25 -> 120 | J8: 45 | K8: 1 | L8: =H8*J8*K8 -> 135000
A9: R003 | B9: HDPE Green | C9: kg | D9: =550+3420 -> 3970 | E9: =SUMIF(RM_Purchase_YTD!C:C,'RM Rollforward'!A9,RM_Purchase_YTD!E:E) -> 900 | F9: =SUMIF(RM_InboundProd_YTD!B:B,'RM Rollforward'!A9,RM_InboundProd_YTD!D:D) -> 2850 | G9: =SUMIF(RM_Outbound_YTD!B:B,'RM Rollforward'!A9,RM_Outbound_YTD!D:D) -> 7720 | H9: =D9+E9+F9-G9 -> 0 | I9: =H9/25 -> 0 | J9: 45 | K9: 1 | L9: =H9*J9*K9 -> 0
A10: R004 | B10: HDPE Black | C10: kg | D10: =75+7200 -> 7275 | E10: =SUMIF(RM_Purchase_YTD!C:C,'RM Rollforward'!A10,RM_Purchase_YTD!E:E) -> 34165 | F10: =SUMIF(RM_InboundProd_YTD!B:B,'RM Rollforward'!A10,RM_InboundProd_YTD!D:D) -> 6825 | G10: =SUMIF(RM_Outbound_YTD!B:B,'RM Rollforward'!A10,RM_Outbound_YTD!D:D) -> 25550 | H10: =D10+E10+F10-G10 -> 22715 | I10: =H10/25 -> 908.6 | J10: 42 | K10: 1 | L10: =H10*J10*K10 -> 954030
A11: R005 | B11: HDPE White | C11: kg | D11: =750+2010 -> 2760 | E11: =SUMIF(RM_Purchase_YTD!C:C,'RM Rollforward'!A11,RM_Purchase_YTD!E:E) -> 28530 | F11: =SUMIF(RM_InboundProd_YTD!B:B,'RM Rollforward'!A11,RM_InboundProd_YTD!D:D) -> 3225 | G11: =SUMIF(RM_Outbound_YTD!B:B,'RM Rollforward'!A11,RM_Outbound_YTD!D:D) -> 29830 | H11: =D11+E11+F11-G11 -> 4685 | I11: =H11/25 -> 187.4 | J11: 48 | K11: 1 | L11: =H11*J11*K11 -> 224880
A12: R006 | B12: HDPE Yellow | C12: kg | D12: 11490 | E12: =SUMIF(RM_Purchase_YTD!C:C,'RM Rollforward'!A12,RM_Purchase_YTD!E:E) -> 2400 | F12: =SUMIF(RM_InboundProd_YTD!B:B,'RM Rollforward'!A12,RM_InboundProd_YTD!D:D) -> 1350 | G12: =SUMIF(RM_Outbound_YTD!B:B,'RM Rollforward'!A12,RM_Outbound_YTD!D:D) -> 15240 | H12: =D12+E12+F12-G12 -> 0 | I12: =H12/25 -> 0 | J12: 45 | K12: 1 | L12: =H12*J12*K12 -> 0
A13: R007 | B13: HDPE Orange | C13: kg | D13: 575 | E13: =SUMIF(RM_Purchase_YTD!C:C,'RM Rollforward'!A13,RM_Purchase_YTD!E:E) -> 0 | F13: =SUMIF(RM_InboundProd_YTD!B:B,'RM Rollforward'!A13,RM_InboundProd_YTD!D:D) -> 1700 | G13: =SUMIF(RM_Outbound_YTD!B:B,'RM Rollforward'!A13,RM_Outbound_YTD!D:D) -> 2250 | H13: =D13+E13+F13-G13 -> 25 | I13: =H13/25 -> 1 | J13: 45 | K13: 1 | L13: =H8*J13*K13 -> 135000
A14: R008 | B14: HDPE Blow Virgin | C14: kg | D14: 975 | E14: =SUMIF(RM_Purchase_YTD!C:C,'RM Rollforward'!A14,RM_Purchase_YTD!E:E) -> 35000 | F14: =SUMIF(RM_InboundProd_YTD!B:B,'RM Rollforward'!A14,RM_InboundProd_YTD!D:D) -> 0 | G14: =SUMIF(RM_Outbound_YTD!B:B,'RM Rollforward'!A14,RM_Outbound_YTD!D:D) -> 17100 | H14: =D14+E14+F14-G14 -> 18875 | I14: =H14/25 -> 755 | J14: 72.5 | K14: 1 | L14: =H14*J14*K14 -> 1368437.5
A15: R009 | B15: HDPE Film Virgin | C15: kg | D15: 23225 | E15: =SUMIF(RM_Purchase_YTD!C:C,'RM Rollforward'!A15,RM_Purchase_YTD!E:E) -> 42500 | F15: =SUMIF(RM_InboundProd_YTD!B:B,'RM Rollforward'!A15,RM_InboundProd_YTD!D:D) -> 0 | G15: =SUMIF(RM_Outbound_YTD!B:B,'RM Rollforward'!A15,RM_Outbound_YTD!D:D) -> 63900 | H15: =D15+E15+F15-G15 -> 1825 | I15: =H15/25 -> 73 | J15: 72.5 | K15: 1 | L15: =H15*J15*K15 -> 132312.5
A16: R011 | B16: LDPE Virgin | C16: kg | D16: 650 | E16: =SUMIF(RM_Purchase_YTD!C:C,'RM Rollforward'!A16,RM_Purchase_YTD!E:E) -> 0 | F16: =SUMIF(RM_InboundProd_YTD!B:B,'RM Rollforward'!A16,RM_InboundProd_YTD!D:D) -> 0 | G16: =SUMIF(RM_Outbound_YTD!B:B,'RM Rollforward'!A16,RM_Outbound_YTD!D:D) -> 0 | H16: =D16+E16+F16-G16 -> 650 | I16: =H16/25 -> 26 | J16: 89 | K16: 1 | L16: =H16*J16*K16 -> 57850
A17: R012 | B17: LLDPE Virgin | C17: kg | D17: 11650 | E17: =SUMIF(RM_Purchase_YTD!C:C,'RM Rollforward'!A17,RM_Purchase_YTD!E:E) -> 17500 | F17: =SUMIF(RM_InboundProd_YTD!B:B,'RM Rollforward'!A17,RM_InboundProd_YTD!D:D) -> 0 | G17: =SUMIF(RM_Outbound_YTD!B:B,'RM Rollforward'!A17,RM_Outbound_YTD!D:D) -> 4525 | H17: =D17+E17+F17-G17 -> 24625 | I17: =H17/25 -> 985 | J17: 77 | K17: 1 | L17: =H17*J17*K17 -> 1896125
A18: R013 | B18: LDPE Recycle | C18: kg | D18: 6050 | E18: =SUMIF(RM_Purchase_YTD!C:C,'RM Rollforward'!A18,RM_Purchase_YTD!E:E) -> 0 | F18: =SUMIF(RM_InboundProd_YTD!B:B,'RM Rollforward'!A18,RM_InboundProd_YTD!D:D) -> 0 | G18: =SUMIF(RM_Outbound_YTD!B:B,'RM Rollforward'!A18,RM_Outbound_YTD!D:D) -> 5150 | H18: =D18+E18+F18-G18 -> 900 | I18: =H18/25 -> 36 | J18: 47 | K18: 1 | L18: =H18*J18*K18 -> 42300
A19: R015 | B19: Dehydrating Agent | C19: kg | D19: 1450 | E19: =SUMIF(RM_Purchase_YTD!C:C,'RM Rollforward'!A19,RM_Purchase_YTD!E:E) -> 0 | F19: =SUMIF(RM_InboundProd_YTD!B:B,'RM Rollforward'!A19,RM_InboundProd_YTD!D:D) -> 0 | G19: =SUMIF(RM_Outbound_YTD!B:B,'RM Rollforward'!A19,RM_Outbound_YTD!D:D) -> 1150 | H19: =D19+E19+F19-G19 -> 300 | I19: =H19/25 -> 12 | J19: 50 | K19: 1 | L19: =H19*J19*K19 -> 15000
A20: R016 | B20: PP Yarn Virgin | C20: kg | D20: 35100 | E20: =SUMIF(RM_Purchase_YTD!C:C,'RM Rollforward'!A20,RM_Purchase_YTD!E:E) -> 17500 | F20: =SUMIF(RM_InboundProd_YTD!B:B,'RM Rollforward'!A20,RM_InboundProd_YTD!D:D) -> 0 | G20: =SUMIF(RM_Outbound_YTD!B:B,'RM Rollforward'!A20,RM_Outbound_YTD!D:D) -> 42300 | H20: =D20+E20+F20-G20 -> 10300 | I20: =H20/25 -> 412 | J20: 70 | K20: 1 | L20: =H20*J20*K20 -> 721000
A21: R018 | B21: PP Film Virgin | C21: kg | D21: 11750 | E21: =SUMIF(RM_Purchase_YTD!C:C,'RM Rollforward'!A21,RM_Purchase_YTD!E:E) -> 10000 | F21: =SUMIF(RM_InboundProd_YTD!B:B,'RM Rollforward'!A21,RM_InboundProd_YTD!D:D) -> 0 | G21: =SUMIF(RM_Outbound_YTD!B:B,'RM Rollforward'!A21,RM_Outbound_YTD!D:D) -> 12000 | H21: =D21+E21+F21-G21 -> 9750 | I21: =H21/25 -> 390 | J21: 71 | K21: 1 | L21: =H21*J21*K21 -> 692250
A22: R019 | B22: PP Recycle Transparent | C22: kg | D22: 0 | E22: =SUMIF(RM_Purchase_YTD!C:C,'RM Rollforward'!A22,RM_Purchase_YTD!E:E) -> 2050 | F22: =SUMIF(RM_InboundProd_YTD!B:B,'RM Rollforward'!A22,RM_InboundProd_YTD!D:D) -> 0 | G22: =SUMIF(RM_Outbound_YTD!B:B,'RM Rollforward'!A22,RM_Outbound_YTD!D:D) -> 2050 | H22: =D22+E22+F22-G22 -> 0 | I22: =H22/25 -> 0 | J22: 57 | K22: 1 | L22: =H22*J22*K22 -> 0
A23: R020 | B23: PP Black | C23: kg | D23: 38150 | E23: =SUMIF(RM_Purchase_YTD!C:C,'RM Rollforward'!A23,RM_Purchase_YTD!E:E) -> 0 | F23: =SUMIF(RM_InboundProd_YTD!B:B,'RM Rollforward'!A23,RM_InboundProd_YTD!D:D) -> 0 | G23: =SUMIF(RM_Outbound_YTD!B:B,'RM Rollforward'!A23,RM_Outbound_YTD!D:D) -> 3025 | H23: =D23+E23+F23-G23 -> 35125 | I23: =H23/25 -> 1405 | J23: 63 | K23: 1 | L23: =H23*J23*K23 -> 2212875
A24: R021 | B24: HDV Blue | C24: kg | D24: 100 | E24: =SUMIF(RM_Purchase_YTD!C:C,'RM Rollforward'!A24,RM_Purchase_YTD!E:E) -> 0 | F24: =SUMIF(RM_InboundProd_YTD!B:B,'RM Rollforward'!A24,RM_InboundProd_YTD!D:D) -> 1550 | G24: =SUMIF(RM_Outbound_YTD!B:B,'RM Rollforward'!A24,RM_Outbound_YTD!D:D) -> 650 | H24: =D24+E24+F24-G24 -> 1000 | I24: =H24/25 -> 40 | J24: 75 | K24: 1 | L24: =H24*J24*K24 -> 75000
A25: R022 | B25: HDV Green | C25: kg | D25: 0 | E25: =SUMIF(RM_Purchase_YTD!C:C,'RM Rollforward'!A25,RM_Purchase_YTD!E:E) -> 0 | F25: =SUMIF(RM_InboundProd_YTD!B:B,'RM Rollforward'!A25,RM_InboundProd_YTD!D:D) -> 0 | G25: =SUMIF(RM_Outbound_YTD!B:B,'RM Rollforward'!A25,RM_Outbound_YTD!D:D) -> 0 | H25: =D25+E25+F25-G25 -> 0 | I25: =H25/25 -> 0 | J25: 75 | K25: 1 | L25: =H25*J25*K25 -> 0
... A33: R030 | B33: PP Injection Recycle | C33: kg | D33: 0 | E33: =SUMIF(RM_Purchase_YTD!C:C,'RM Rollforward'!A33,RM_Purchase_YTD!E:E) -> 0 | F33: =SUMIF(RM_InboundProd_YTD!B:B,'RM Rollforward'!A33,RM_InboundProd_YTD!D:D) -> 0 | G33: =SUMIF(RM_Outbound_YTD!B:B,'RM Rollforward'!A33,RM_Outbound_YTD!D:D) -> 0 | H33: =D33+E33+F33-G33 -> 0 | I33: =H33/25 -> 0 | J33: 42 | K33: 1 | L33: =H33*J33*K33 -> 0
A34: R031 | B34: PET Resin | C34: kg | D34: 4400 | E34: =SUMIF(RM_Purchase_YTD!C:C,'RM Rollforward'!A34,RM_Purchase_YTD!E:E) -> 0 | F34: =SUMIF(RM_InboundProd_YTD!B:B,'RM Rollforward'!A34,RM_InboundProd_YTD!D:D) -> 0 | G34: =SUMIF(RM_Outbound_YTD!B:B,'RM Rollforward'!A34,RM_Outbound_YTD!D:D) -> 0 | H34: =D34+E34+F34-G34 -> 4400 | I34: =H34/1100 -> 4 | J34: 75 | K34: 1 | L34: =H34*J34*K34 -> 330000
A35: R032 | B35: HDPE Injection | C35: kg | D35: 1275 | E35: =SUMIF(RM_Purchase_YTD!C:C,'RM Rollforward'!A35,RM_Purchase_YTD!E:E) -> 2500 | F35: =SUMIF(RM_InboundProd_YTD!B:B,'RM Rollforward'!A35,RM_InboundProd_YTD!D:D) -> 0 | G35: =SUMIF(RM_Outbound_YTD!B:B,'RM Rollforward'!A35,RM_Outbound_YTD!D:D) -> 0 | H35: =D35+E35+F35-G35 -> 3775 | I35: =H35/25 -> 151 | J35: 76 | K35: 1 | L35: =H35*J35*K35 -> 286900
A36: R033 | B36: LDPE Inejction | C36: kg | D36: 1200 | E36: =SUMIF(RM_Purchase_YTD!C:C,'RM Rollforward'!A36,RM_Purchase_YTD!E:E) -> 0 | F36: =SUMIF(RM_InboundProd_YTD!B:B,'RM Rollforward'!A36,RM_InboundProd_YTD!D:D) -> 0 | G36: =SUMIF(RM_Outbound_YTD!B:B,'RM Rollforward'!A36,RM_Outbound_YTD!D:D) -> 0 | H36: =D36+E36+F36-G36 -> 1200 | I36: =H36/25 -> 48 | J36: 74 | K36: 1 | L36: =H36*J36*K36 -> 88800
A37: R034 | B37: Clarifying Agent (bags) | C37: kg | D37: 125 | E37: =SUMIF(RM_Purchase_YTD!C:C,'RM Rollforward'!A37,RM_Purchase_YTD!E:E) -> 0 | F37: =SUMIF(RM_InboundProd_YTD!B:B,'RM Rollforward'!A37,RM_InboundProd_YTD!D:D) -> 0 | G37: =SUMIF(RM_Outbound_YTD!B:B,'RM Rollforward'!A37,RM_Outbound_YTD!D:D) -> 75 | H37: =D37+E37+F37-G37 -> 50 | I37: =H37/25 -> 2 | J37: 40 | K37: 1 | L37: =H37*J37*K37 -> 2000
A38: COL001 | B38: SB Colorant D6 Blue | C38: kg | D38: 885 | E38: =SUMIF(RM_Purchase_YTD!C:C,'RM Rollforward'!A38,RM_Purchase_YTD!E:E) -> 1000 | F38: =SUMIF(RM_InboundProd_YTD!B:B,'RM Rollforward'!A38,RM_InboundProd_YTD!D:D) -> 0 | G38: =SUMIF(RM_Outbound_YTD!B:B,'RM Rollforward'!A38,RM_Outbound_YTD!D:D) -> 585 | H38: =D38+E38+F38-G38 -> 1300 | J38: 168 | K38: 1 | L38: =H38*J38*K38 -> 218400
A39: COL002 | B39: SB Colorant D4 Green | C39: kg | D39: 619 | E39: =SUMIF(RM_Purchase_YTD!C:C,'RM Rollforward'!A39,RM_Purchase_YTD!E:E) -> 1000 | F39: =SUMIF(RM_InboundProd_YTD!B:B,'RM Rollforward'!A39,RM_InboundProd_YTD!D:D) -> 0 | G39: =SUMIF(RM_Outbound_YTD!B:B,'RM Rollforward'!A39,RM_Outbound_YTD!D:D) -> 175 | H39: =D39+E39+F39-G39 -> 1444 | J39: 201 | K39: 1 | L39: =H39*J39*K39 -> 290244
A40: COL003 | B40: SB Colorant D5 Orange | C40: kg | D40: 975 | E40: =SUMIF(RM_Purchase_YTD!C:C,'RM Rollforward'!A40,RM_Purchase_YTD!E:E) -> 750 | F40: =SUMIF(RM_InboundProd_YTD!B:B,'RM Rollforward'!A40,RM_InboundProd_YTD!D:D) -> 0 | G40: =SUMIF(RM_Outbound_YTD!B:B,'RM Rollforward'!A40,RM_Outbound_YTD!D:D) -> 128 | H40: =D40+E40+F40-G40 -> 1597 | J40: 241 | K40: 1 | L40: =H40*J40*K40 -> 384877
A41: COL004 | B41: SB Colorant D8 Red | C41: kg | D41: 953 | E41: =SUMIF(RM_Purchase_YTD!C:C,'RM Rollforward'!A41,RM_Purchase_YTD!E:E) -> 1000 | F41: =SUMIF(RM_InboundProd_YTD!B:B,'RM Rollforward'!A41,RM_InboundProd_YTD!D:D) -> 0 | G41: =SUMIF(RM_Outbound_YTD!B:B,'RM Rollforward'!A41,RM_Outbound_YTD!D:D) -> 328 | H41: =D41+E41+F41-G41 -> 1625 | J41: 188 | K41: 1 | L41: =H41*J41*K41 -> 305500
A42: COL005 | B42: SB Colorant 116 White | C42: kg | D42: 450 | E42: =SUMIF(RM_Purchase_YTD!C:C,'RM Rollforward'!A42,RM_Purchase_YTD!E:E) -> 1000 | F42: =SUMIF(RM_InboundProd_YTD!B:B,'RM Rollforward'!A42,RM_InboundProd_YTD!D:D) -> 0 | G42: =SUMIF(RM_Outbound_YTD!B:B,'RM Rollforward'!A42,RM_Outbound_YTD!D:D) -> 525 | H42: =D42+E42+F42-G42 -> 925 | J42: 160 | K42: 1 | L42: =H42*J42*K42 -> 148000
A43: COL006 | B43: SB Colorant D7 Yellow | C43: kg | D43: 525 | E43: =SUMIF(RM_Purchase_YTD!C:C,'RM Rollforward'!A43,RM_Purchase_YTD!E:E) -> 750 | F43: =SUMIF(RM_InboundProd_YTD!B:B,'RM Rollforward'!A43,RM_InboundProd_YTD!D:D) -> 0 | G43: =SUMIF(RM_Outbound_YTD!B:B,'RM Rollforward'!A43,RM_Outbound_YTD!D:D) -> 180 | H43: =D43+E43+F43-G43 -> 1095 | J43: 184 | K43: 1 | L43: =H43*J43*K43 -> 201480
A44: COL007 | B44: Colorant Black 0025 | C44: kg | D44: 640 | E44: =SUMIF(RM_Purchase_YTD!C:C,'RM Rollforward'!A44,RM_Purchase_YTD!E:E) -> 1000 | F44: =SUMIF(RM_InboundProd_YTD!B:B,'RM Rollforward'!A44,RM_InboundProd_YTD!D:D) -> 0 | G44: =SUMIF(RM_Outbound_YTD!B:B,'RM Rollforward'!A44,RM_Outbound_YTD!D:D) -> 566 | H44: =D44+E44+F44-G44 -> 1074 | J44: 84 | K44: 1 | L44: =H44*J44*K44 -> 90216
A45: COL008 | B45: Colorant Blue#5 | C45: kg | D45: 350 | E45: =SUMIF(RM_Purchase_YTD!C:C,'RM Rollforward'!A45,RM_Purchase_YTD!E:E) -> 0 | F45: =SUMIF(RM_InboundProd_YTD!B:B,'RM Rollforward'!A45,RM_InboundProd_YTD!D:D) -> 0 | G45: =SUMIF(RM_Outbound_YTD!B:B,'RM Rollforward'!A45,RM_Outbound_YTD!D:D) -> 25 | H45: =D45+E45+F45-G45 -> 325 | J45: 130 | K45: 1 | L45: =H45*J45*K45 -> 42250
A46: COL009 | B46: Colorant Bluish White | C46: kg | D46: 425 | E46: =SUMIF(RM_Purchase_YTD!C:C,'RM Rollforward'!A46,RM_Purchase_YTD!E:E) -> 0 | F46: =SUMIF(RM_InboundProd_YTD!B:B,'RM Rollforward'!A46,RM_InboundProd_YTD!D:D) -> 0 | G46: =SUMIF(RM_Outbound_YTD!B:B,'RM Rollforward'!A46,RM_Outbound_YTD!D:D) -> 50 | H46: =D46+E46+F46-G46 -> 375 | J46: 130 | K46: 1 | L46: =H46*J46*K46 -> 48750
A47: COL012 | B47: Colorant Pink | C47: kg | D47: 100 | E47: =SUMIF(RM_Purchase_YTD!C:C,'RM Rollforward'!A47,RM_Purchase_YTD!E:E) -> 0 | F47: =SUMIF(RM_InboundProd_YTD!B:B,'RM Rollforward'!A47,RM_InboundProd_YTD!D:D) -> 0 | G47: =SUMIF(RM_Outbound_YTD!B:B,'RM Rollforward'!A47,RM_Outbound_YTD!D:D) -> 0 | H47: =D47+E47+F47-G47 -> 100 | J47: 156 | K47: 1 | L47: =H47*J47*K47 -> 15600
A48: R103 | B48: PET Bottle Pre-Formed 12g (30mm) | C48: pcs | D48: 80000 | E48: =SUMIF(RM_Purchase_YTD!C:C,'RM Rollforward'!A48,RM_Purchase_YTD!E:E) -> 55000 | F48: =SUMIF(RM_InboundProd_YTD!B:B,'RM Rollforward'!A48,RM_InboundProd_YTD!D:D) -> 0 | G48: =SUMIF(RM_Outbound_YTD!B:B,'RM Rollforward'!A48,RM_Outbound_YTD!D:D) -> 135000 | H48: =D48+E48+F48-G48 -> 0 | J48: 1.3 | K48: 1 | L48: =H48*J48*K48 -> 0
A49: R104 | B49: PET Bottle Pre-Formed 12g (26mm) (RGMC) | C49: pcs | D49: 33000 | E49: =SUMIF(RM_Purchase_YTD!C:C,'RM Rollforward'!A49,RM_Purchase_YTD!E:E) -> 0 | F49: =SUMIF(RM_InboundProd_YTD!B:B,'RM Rollforward'!A49,RM_InboundProd_YTD!D:D) -> 0 | G49: =SUMIF(RM_Outbound_YTD!B:B,'RM Rollforward'!A49,RM_Outbound_YTD!D:D) -> 0 | H49: =D49+E49+F49-G49 -> 33000 | J49: 1.3 | K49: 1 | L49: =H49*J49*K49 -> 42900
... A527: VR003 | B527: Virgin Roll Mini White | C527: kg | D527: 33 | E527: =SUMIF(RM_Purchase_YTD!C:C,'RM Rollforward'!A527,RM_Purchase_YTD!E:E) -> 0 | F527: =SUMIF(RM_InboundProd_YTD!B:B,'RM Rollforward'!A527,RM_InboundProd_YTD!D:D) -> 3327 | G527: =SUMIF(RM_Outbound_YTD!B:B,'RM Rollforward'!A527,RM_Outbound_YTD!D:D) -> 3360 | H527: =D527+E527+F527-G527 -> 0 | J527: 75 | K527: 1 | L527: =H527*J527*K527 -> 0
A528: VR004 | B528: Virgin Roll Mini Blue | C528: kg | D528: 0 | E528: =SUMIF(RM_Purchase_YTD!C:C,'RM Rollforward'!A528,RM_Purchase_YTD!E:E) -> 0 | F528: 0 | G528: =SUMIF(RM_Outbound_YTD!B:B,'RM Rollforward'!A528,RM_Outbound_YTD!D:D) -> 0 | H528: =D528+E528+F528-G528 -> 0 | J528: 75 | K528: 1 | L528: =H528*J528*K528 -> 0
A529: VR005 | B529: Virgin Roll Mini Orange | C529: kg | D529: 0 | E529: =SUMIF(RM_Purchase_YTD!C:C,'RM Rollforward'!A529,RM_Purchase_YTD!E:E) -> 0 | F529: =SUMIF(RM_InboundProd_YTD!B:B,'RM Rollforward'!A529,RM_InboundProd_YTD!D:D) -> 0 | G529: =SUMIF(RM_Outbound_YTD!B:B,'RM Rollforward'!A529,RM_Outbound_YTD!D:D) -> 0 | H529: =D529+E529+F529-G529 -> 0 | J529: 75 | K529: 1 | L529: =H529*J529*K529 -> 0
A530: VR006 | B530: Virgin Roll Mini Red | C530: kg | D530: 0 | E530: =SUMIF(RM_Purchase_YTD!C:C,'RM Rollforward'!A530,RM_Purchase_YTD!E:E) -> 0 | F530: =SUMIF(RM_InboundProd_YTD!B:B,'RM Rollforward'!A530,RM_InboundProd_YTD!D:D) -> 0 | G530: =SUMIF(RM_Outbound_YTD!B:B,'RM Rollforward'!A530,RM_Outbound_YTD!D:D) -> 0 | H530: =D530+E530+F530-G530 -> 0 | J530: 75 | K530: 1 | L530: =H530*J530*K530 -> 0
A531: VR007 | B531: Virgin Roll Mini Yellow | C531: kg | D531: 0 | E531: =SUMIF(RM_Purchase_YTD!C:C,'RM Rollforward'!A531,RM_Purchase_YTD!E:E) -> 0 | F531: =SUMIF(RM_InboundProd_YTD!B:B,'RM Rollforward'!A531,RM_InboundProd_YTD!D:D) -> 0 | G531: =SUMIF(RM_Outbound_YTD!B:B,'RM Rollforward'!A531,RM_Outbound_YTD!D:D) -> 0 | H531: =D531+E531+F531-G531 -> 0 | J531: 75 | K531: 1 | L531: =H531*J531*K531 -> 0
A532: VR008 | B532: Virgin Roll Mini Green | C532: kg | D532: 0 | E532: =SUMIF(RM_Purchase_YTD!C:C,'RM Rollforward'!A532,RM_Purchase_YTD!E:E) -> 0 | F532: =SUMIF(RM_InboundProd_YTD!B:B,'RM Rollforward'!A532,RM_InboundProd_YTD!D:D) -> 0 | G532: =SUMIF(RM_Outbound_YTD!B:B,'RM Rollforward'!A532,RM_Outbound_YTD!D:D) -> 0 | H532: =D532+E532+F532-G532 -> 0 | J532: 75 | K532: 1 | L532: =H532*J532*K532 -> 0
A533: VR009 | B533: Virgin Roll Tiny Transparent | C533: kg | D533: 163 | E533: =SUMIF(RM_Purchase_YTD!C:C,'RM Rollforward'!A533,RM_Purchase_YTD!E:E) -> 0 | F533: =SUMIF(RM_InboundProd_YTD!B:B,'RM Rollforward'!A533,RM_InboundProd_YTD!D:D) -> 5128 | G533: =SUMIF(RM_Outbound_YTD!B:B,'RM Rollforward'!A533,RM_Outbound_YTD!D:D) -> 4981 | H533: =D533+E533+F533-G533 -> 310 | J533: 75 | K533: 1 | L533: =H533*J533*K533 -> 23250
A534: VR011 | B534: Virgin Roll Tiny White | C534: kg | D534: 133 | E534: =SUMIF(RM_Purchase_YTD!C:C,'RM Rollforward'!A534,RM_Purchase_YTD!E:E) -> 0 | F534: =SUMIF(RM_InboundProd_YTD!B:B,'RM Rollforward'!A534,RM_InboundProd_YTD!D:D) -> 231 | G534: =SUMIF(RM_Outbound_YTD!B:B,'RM Rollforward'!A534,RM_Outbound_YTD!D:D) -> 337 | H534: =D534+E534+F534-G534 -> 27 | J534: 75 | K534: 1 | L534: =H534*J534*K534 -> 2025
A535: VR012 | B535: Virgin Roll Tiny Blue | C535: kg | D535: 0 | E535: =SUMIF(RM_Purchase_YTD!C:C,'RM Rollforward'!A535,RM_Purchase_YTD!E:E) -> 0 | F535: =SUMIF(RM_InboundProd_YTD!B:B,'RM Rollforward'!A535,RM_InboundProd_YTD!D:D) -> 782 | G535: =SUMIF(RM_Outbound_YTD!B:B,'RM Rollforward'!A535,RM_Outbound_YTD!D:D) -> 744 | H535: =D535+E535+F535-G535 -> 38 | J535: 75 | K535: 1 | L535: =H535*J535*K535 -> 2850
A536: VR013 | B536: Virgin Roll Tiny Orange | C536: kg | D536: 0 | E536: =SUMIF(RM_Purchase_YTD!C:C,'RM Rollforward'!A536,RM_Purchase_YTD!E:E) -> 0 | F536: =SUMIF(RM_InboundProd_YTD!B:B,'RM Rollforward'!A536,RM_InboundProd_YTD!D:D) -> 876 | G536: =SUMIF(RM_Outbound_YTD!B:B,'RM Rollforward'!A536,RM_Outbound_YTD!D:D) -> 629 | H536: =D536+E536+F536-G536 -> 247 | J536: 75 | K536: 1 | L536: =H536*J536*K536 -> 18525
A537: VR014 | B537: Virgin Roll Tiny Red | C537: kg | D537: 0 | E537: =SUMIF(RM_Purchase_YTD!C:C,'RM Rollforward'!A537,RM_Purchase_YTD!E:E) -> 0 | F537: =SUMIF(RM_InboundProd_YTD!B:B,'RM Rollforward'!A537,RM_InboundProd_YTD!D:D) -> 0 | G537: =SUMIF(RM_Outbound_YTD!B:B,'RM Rollforward'!A537,RM_Outbound_YTD!D:D) -> 0 | H537: =D537+E537+F537-G537 -> 0 | J537: 75 | K537: 1 | L537: =H537*J537*K537 -> 0
A538: VR015 | B538: Virgin Roll Tiny Yellow | C538: kg | D538: 0 | E538: =SUMIF(RM_Purchase_YTD!C:C,'RM Rollforward'!A538,RM_Purchase_YTD!E:E) -> 0 | F538: =SUMIF(RM_InboundProd_YTD!B:B,'RM Rollforward'!A538,RM_InboundProd_YTD!D:D) -> 0 | G538: =SUMIF(RM_Outbound_YTD!B:B,'RM Rollforward'!A538,RM_Outbound_YTD!D:D) -> 0 | H538: =D538+E538+F538-G538 -> 0 | J538: 75 | K538: 1 | L538: =H538*J538*K538 -> 0
A539: VR016 | B539: Virgin Roll Tiny Green | C539: kg | D539: 33 | E539: =SUMIF(RM_Purchase_YTD!C:C,'RM Rollforward'!A539,RM_Purchase_YTD!E:E) -> 0 | F539: =SUMIF(RM_InboundProd_YTD!B:B,'RM Rollforward'!A539,RM_InboundProd_YTD!D:D) -> 825 | G539: =SUMIF(RM_Outbound_YTD!B:B,'RM Rollforward'!A539,RM_Outbound_YTD!D:D) -> 825 | H539: =D539+E539+F539-G539 -> 33 | J539: 75 | K539: 1 | L539: =H539*J539*K539 -> 2475
A540: VR017 | B540: Virgin Roll Medium Transparent | C540: kg | D540: 484 | E540: =SUMIF(RM_Purchase_YTD!C:C,'RM Rollforward'!A540,RM_Purchase_YTD!E:E) -> 0 | F540: =SUMIF(RM_InboundProd_YTD!B:B,'RM Rollforward'!A540,RM_InboundProd_YTD!D:D) -> 2995 | G540: =SUMIF(RM_Outbound_YTD!B:B,'RM Rollforward'!A540,RM_Outbound_YTD!D:D) -> 2969 | H540: =D540+E540+F540-G540 -> 510 | J540: 75 | K540: 1 | L540: =H540*J540*K540 -> 38250
... A674: RR004-19 | B674: Recycled Roll E Large Black (Kgs) | C674: kg | D674: 0 | E674: =SUMIF(RM_Purchase_YTD!C:C,'RM Rollforward'!A674,RM_Purchase_YTD!E:E) -> 0 | F674: =SUMIF(RM_InboundProd_YTD!B:B,'RM Rollforward'!A674,RM_InboundProd_YTD!D:D) -> 0 | G674: =SUMIF(RM_Outbound_YTD!B:B,'RM Rollforward'!A674,RM_Outbound_YTD!D:D) -> 0 | H674: =D674+E674+F674-G674 -> 0 | J674: 45 | K674: 1 | L674: =H674*J674*K674 -> 0
H675: =sum(H514:H674) -> 35306

Sheet Inbound Form
B1: Rivson Goldplast Manufacturing Corp | G1: 000169
B2: PRK Paho Brgy Felisa Bacolod City
A3: I N B O U N D F O R M
A5: Supplier: | C5: PO Number: | F5: Date Rvd: 06/19/2025
A7: SKU Code | B7: SKU Description | C7: In QTY | D7: UOM | F7: Van Num | G7: Remarks
A8: R001 | B8: HDPE Blue | C8: 630 | E8: JP | F8: DRYU 2634054
A9: R002 | B9: HDPE Red | C9: 1770
A10: R005 | B10: HDPE White | C10: 9570
A11: R032 | B11: HDPE Injection | C11: 2500
A12: R103 | B12: PET Bottle Pre-Formed 12g (30mm) | C12: 25000
A21: Signature
A23: Name
F24: Kimberly Pedres
A25: Date
B27: Rivson Goldplast Manufacturing Corp | G27: =G1 -> 000169
B28: PRK Paho Brgy Felisa Bacolod City
A29: I N B O U N D F O R M
A31: Supplier: | C31: PO Number: | F31: =F5 -> Date Rvd: 06/19/2025
A33: SKU Code | B33: SKU Description | C33: In QTY | D33: UOM | F33: Van Num | G33: Remarks
A34: =A8 -> R001 | B34: =B8 -> HDPE Blue | C34: =C8 -> 630 | E34: =E8 -> JP | F34: =F8 -> DRYU 2634054
A35: =A9 -> R002 | B35: =B9 -> HDPE Red | C35: =C9 -> 1770 | E35: =E9 | F35: =F9
A36: =A10 -> R005 | B36: =B10 -> HDPE White | C36: =C10 -> 9570 | E36: =E10 | F36: =F10
A37: =A11 -> R032 | B37: =B11 -> HDPE Injection | C37: =C11 -> 2500 | E37: =E11 | F37: =F11
A38: =A12 -> R103 | B38: =B12 -> PET Bottle Pre-Formed 12g (30mm) | C38: =C12 -> 25000 | E38: =E12 | F38: =F12
A39: =A13 | B39: =B13 | C39: =C13 | E39: =E13 | F39: =F13
A40: =A14 | B40: =B14 | C40: =C14 | E40: =E14 | F40: =F14
A41: =A15 | B41: =B15 | C41: =C15 | E41: =E15 | F41: =F15
A42: =A16 | B42: =B16 | C42: =C16 | E42: =E16 | F42: =F16
A43: =A17 | B43: =B17 | C43: =C17 | F43: =F17
A44: =A18 | B44: =B18 | C44: =C18 | E44: =E18 | F44: =F18
A45: =A19 | B45: =B19 | C45: =C19
A46: =A20 | B46: =B20 | C46: =C20
B47: Receiver: | D47: Bookkeeping: | F47: Inventory:
A49: Signature
A51: Name
F52: Kimberly Pedres
A53: Date

Sheet High-Low Inv
A2: SKU | B2: Item Description | C2: Critical | E2: Low | G2: Moderate | I2: High | K2: Ave. Daily Consumption in bags
C3: 1-7 Days | D3: In Bags | E3: 8-15 Days | F3: In Bags | G3: 15-25 Days | H3: In Bags | I3: 25-30 Days | J3: In Bags | L3: Convertion | M3: In KG
A4: R001 | B4: HDPE Blue | C4: =M4*7 -> 10500 | D4: =C4/L4 -> 350 | E4: =M4*15 -> 22500 | F4: =E4/L4 -> 750 | G4: =M4*25 -> 37500 | H4: =G4/L4 -> 1250 | I4: =M4*30 -> 45000 | J4: =I4/L4 -> 1500 | K4: 50 | L4: 30 | M4: =K4*L4 -> 1500
A5: R002 | B5: HDPE Red | C5: =M5*7 -> 10500 | D5: =C5/L5 -> 350 | E5: =M5*15 -> 22500 | F5: =E5/L5 -> 750 | G5: =M5*25 -> 37500 | H5: =G5/L5 -> 1250 | I5: =M5*30 -> 45000 | J5: =I5/L5 -> 1500 | K5: 50 | L5: 30 | M5: =K5*L5 -> 1500
A6: R003 | B6: HDPE Green | C6: =M6*7 -> 10500 | D6: =C6/L6 -> 350 | E6: =M6*15 -> 22500 | F6: =E6/L6 -> 750 | G6: =M6*25 -> 37500 | H6: =G6/L6 -> 1250 | I6: =M6*30 -> 45000 | J6: =I6/L6 -> 1500 | K6: 50 | L6: 30 | M6: =K6*L6 -> 1500
A7: R004 | B7: HDPE Black | C7: =M7*7 -> 33600 | D7: =C7/L7 -> 1120 | E7: =M7*15 -> 72000 | F7: =E7/L7 -> 2400 | G7: 90000 | H7: =G7/L7 -> 3000 | I7: =M7*30 -> 144000 | J7: =I7/L7 -> 4800 | K7: 160 | L7: 30 | M7: =K7*L7 -> 4800
A8: R005 | B8: HDPE White | C8: =M8*7 -> 10500 | D8: =C8/L8 -> 350 | E8: =M8*15 -> 22500 | F8: =E8/L8 -> 750 | G8: =M8*25 -> 37500 | H8: =G8/L8 -> 1250 | I8: =M8*30 -> 45000 | J8: =I8/L8 -> 1500 | K8: 50 | L8: 30 | M8: =K8*L8 -> 1500
A9: R006 | B9: HDPE Yellow | C9: =M9*7 -> 0 | E9: =M9*15 -> 0 | G9: =M9*25 -> 0 | I9: =M9*30 -> 0 | M9: =K9*L9 -> 0
A10: R007 | B10: HDPE Orange | C10: =M10*7 -> 0 | E10: =M10*15 -> 0 | G10: =M10*25 -> 0 | I10: =M10*30 -> 0 | M10: =K10*L10 -> 0
A11: R008 | B11: HDPE Blow Virgin | C11: =M11*7 -> 5950 | D11: =C11/L11 -> 238 | E11: =M11*15 -> 12750 | F11: =E11/L11 -> 510 | G11: =M11*25 -> 21250 | H11: =G11/L11 -> 850 | I11: =M11*30 -> 25500 | J11: =I11/L11 -> 1020 | K11: 34 | L11: 25 | M11: =K11*L11 -> 850
A12: R009 | B12: HDPE Film Virgin | C12: =M12*7 -> 26250 | D12: =C12/L12 -> 1050 | E12: =M12*15 -> 56250 | F12: =E12/L12 -> 2250 | G12: =M12*25 -> 93750 | H12: =G12/L12 -> 3750 | I12: =M12*30 -> 112500 | J12: =I12/L12 -> 4500 | K12: 150 | L12: 25 | M12: =K12*L12 -> 3750
A13: R010 | B13: HDPE Transparent | C13: =M13*7 -> 0 | E13: =M13*15 -> 0 | G13: =M13*25 -> 0 | I13: =M13*30 -> 0 | M13: =K13*L13 -> 0
A14: R011 | B14: LDPE Virgin | C14: =M14*7 -> 0 | E14: =M14*15 -> 0 | G14: =M14*25 -> 0 | I14: =M14*30 -> 0 | M14: =K14*L14 -> 0
A15: R012 | B15: LLDPE Virgin | C15: =M15*7 -> 0 | E15: =M15*15 -> 0 | G15: 10000 | H15: =G15/L15 -> 400 | I15: =M15*30 -> 0 | L15: 25 | M15: =K15*L15 -> 0
A16: R013 | B16: LDPE Recycle | C16: =M16*7 -> 2100 | D16: =C16/L16 -> 70 | E16: =M16*15 -> 4500 | F16: =E16/L16 -> 150 | G16: =M16*25 -> 7500 | H16: =G16/L16 -> 250 | I16: =M16*30 -> 9000 | J16: =I16/L16 -> 300 | K16: 10 | L16: 30 | M16: =K16*L16 -> 300
A17: R014 | B17: MLDPE Virgin | C17: =M17*7 -> 0 | E17: =M17*15 -> 0 | G17: =M17*25 -> 0 | I17: =M17*30 -> 0 | M17: =K17*L17 -> 0
A18: R015 | B18: Dehydrating Agent | C18: =M18*7 -> 0 | E18: =M18*15 -> 0 | G18: =M18*25 -> 0 | I18: =M18*30 -> 0 | M18: =K18*L18 -> 0
A19: R016 | B19: PP Yarn Virgin | C19: =M19*7 -> 18550 | D19: =C19/L19 -> 742 | E19: =M19*15 -> 39750 | F19: =E19/L19 -> 1590 | G19: =M19*25 -> 66250 | H19: =G19/L19 -> 2650 | I19: =M19*30 -> 79500 | J19: =I19/L19 -> 3180 | K19: 106 | L19: 25 | M19: =K19*L19 -> 2650
A20: R017 | B20: PP Thermoforming Virgin Evalene PHT0171 | C20: =M20*7 -> 0 | E20: =M20*15 -> 0 | G20: =M20*25 -> 0 | I20: =M20*30 -> 0 | M20: =K20*L20 -> 0
A21: R018 | B21: PP Film Virgin | C21: =M21*7 -> 7000 | D21: =C21/L21 -> 280 | E21: =M21*15 -> 15000 | F21: =E21/L21 -> 600 | G21: 17500 | H21: =G21/L21 -> 700 | I21: =M21*30 -> 30000 | J21: =I21/L21 -> 1200 | K21: 40 | L21: 25 | M21: =K21*L21 -> 1000
A22: R019 | B22: PP Recycle Transparent | C22: =M22*7 -> 4900 | D22: =C22/L22 -> 196 | E22: =M22*15 -> 10500 | F22: =E22/L22 -> 420 | G22: 18000 | H22: =G22/L22 -> 720 | I22: =M22*30 -> 21000 | J22: =I22/L22 -> 840 | K22: 28 | L22: 25 | M22: =K22*L22 -> 700
A23: R020 | B23: PP Black | C23: =M23*7 -> 0 | E23: =M23*15 -> 0 | G23: =M23*25 -> 0 | I23: =M23*30 -> 0 | M23: =K23*L23 -> 0
A24: R021 | B24: HDV Blue | C24: =M24*7 -> 0 | E24: =M24*15 -> 0 | G24: =M24*25 -> 0 | I24: =M24*30 -> 0 | M24: =K24*L24 -> 0
A25: R022 | B25: HDV Green | C25: =M25*7 -> 0 | E25: =M25*15 -> 0 | G25: =M25*25 -> 0 | I25: =M25*30 -> 0 | M25: =K25*L25 -> 0
A26: R023 | B26: HDV Orange | C26: =M26*7 -> 0 | E26: =M26*15 -> 0 | G26: =M26*25 -> 0 | I26: =M26*30 -> 0 | M26: =K26*L26 -> 0
A27: R024 | B27: HDV Pink | C27: =M27*7 -> 0 | E27: =M27*15 -> 0 | G27: =M27*25 -> 0 | I27: =M27*30 -> 0 | M27: =K27*L27 -> 0
A28: R025 | B28: HDV Red | C28: =M28*7 -> 0 | E28: =M28*15 -> 0 | G28: =M28*25 -> 0 | I28: =M28*30 -> 0 | M28: =K28*L28 -> 0
A29: R026 | B29: HDV Transparent | C29: =M29*7 -> 0 | E29: =M29*15 -> 0 | G29: =M29*25 -> 0 | I29: =M29*30 -> 0 | M29: =K29*L29 -> 0
A30: R027 | B30: HDV White | C30: =M30*7 -> 0 | E30: =M30*15 -> 0 | G30: =M30*25 -> 0 | I30: =M30*30 -> 0 | M30: =K30*L30 -> 0
A31: R028 | B31: HDV Yellow | C31: =M31*7 -> 0 | E31: =M31*15 -> 0 | G31: =M31*25 -> 0 | I31: =M31*30 -> 0 | M31: =K31*L31 -> 0
A32: R029 | B32: PP Injection Virgin | C32: =M32*7 -> 2800 | D32: =C32/L32 -> 112 | E32: =M32*15 -> 6000 | F32: =E32/L32 -> 240 | G32: =M32*25 -> 10000 | H32: =G32/L32 -> 400 | I32: =M32*30 -> 12000 | J32: =I32/L32 -> 480 | K32: 16 | L32: 25 | M32: =K32*L32 -> 400
A33: R030 | B33: PP Injection Recycle | C33: =M33*7 -> 1750 | D33: =C33/L33 -> 70 | E33: =M33*15 -> 3750 | F33: =E33/L33 -> 150 | G33: =M33*25 -> 6250 | H33: =G33/L33 -> 250 | I33: =M33*30 -> 7500 | J33: =I33/L33 -> 300 | K33: 10 | L33: 25 | M33: =K33*L33 -> 250
A34: R031 | B34: PET Resin | C34: =M34*7 -> 7700 | D34: =C34/L34 -> 7 | E34: =M34*15 -> 16500 | F34: =E34/L34 -> 15 | G34: =M34*25 -> 27500 | H34: =G34/L34 -> 25 | I34: =M34*30 -> 33000 | J34: =I34/L34 -> 30 | K34: 1 | L34: 1100 | M34: =K34*L34 -> 1100
A35: R032 | B35: HDPE Injection | C35: =M35*7 -> 3500 | D35: =C35/L35 -> 140 | E35: =M35*15 -> 7500 | F35: =E35/L35 -> 300 | G35: =M35*25 -> 12500 | H35: =G35/L35 -> 500 | I35: =M35*30 -> 15000 | J35: =I35/L35 -> 600 | K35: 20 | L35: 25 | M35: =K35*L35 -> 500
A36: R033 | B36: LDPE Inejction | C36: =M36*7 -> 350 | D36: =C36/L36 -> 14 | E36: =M36*15 -> 750 | F36: =E36/L36 -> 30 | G36: =M36*25 -> 1250 | H36: =G36/L36 -> 50 | I36: =M36*30 -> 1500 | J36: =I36/L36 -> 60 | K36: 2 | L36: 25 | M36: =K36*L36 -> 50
A37: COL001 | B37: SB Colorant D6 Blue | C37: =M37*7 -> 350 | D37: =C37/L37 -> 14 | E37: =M37*15 -> 750 | F37: =E37/L37 -> 30 | G37: =M37*25 -> 1250 | H37: =G37/L37 -> 50 | I37: =M37*30 -> 1500 | J37: =I37/L37 -> 60 | K37: 2 | L37: 25 | M37: =K37*L37 -> 50
A38: COL002 | B38: SB Colorant D4 Green | C38: =M38*7 -> 175 | D38: =C38/L38 -> 7 | E38: =M38*15 -> 375 | F38: =E38/L38 -> 15 | G38: =M38*25 -> 625 | H38: =G38/L38 -> 25 | I38: =M38*30 -> 750 | J38: =I38/L38 -> 30 | K38: 1 | L38: 25 | M38: =K38*L38 -> 25
A39: COL003 | B39: SB Colorant D5 Orange | C39: =M39*7 -> 175 | D39: =C39/L39 -> 7 | E39: =M39*15 -> 375 | F39: =E39/L39 -> 15 | G39: =M39*25 -> 625 | H39: =G39/L39 -> 25 | I39: =M39*30 -> 750 | J39: =I39/L39 -> 30 | K39: 1 | L39: 25 | M39: =K39*L39 -> 25
A40: COL004 | B40: SB Colorant D8 Red | C40: =M40*7 -> 350 | D40: =C40/L40 -> 14 | E40: =M40*15 -> 750 | F40: =E40/L40 -> 30 | G40: =M40*25 -> 1250 | H40: =G40/L40 -> 50 | I40: =M40*30 -> 1500 | J40: =I40/L40 -> 60 | K40: 2 | L40: 25 | M40: =K40*L40 -> 50
A41: COL005 | B41: SB Colorant 116 White | C41: =M41*7 -> 175 | D41: =C41/L41 -> 7 | E41: =M41*15 -> 375 | F41: =E41/L41 -> 15 | G41: =M41*25 -> 625 | H41: =G41/L41 -> 25 | I41: =M41*30 -> 750 | J41: =I41/L41 -> 30 | K41: 1 | L41: 25 | M41: =K41*L41 -> 25
A42: COL006 | B42: SB Colorant D7 Yellow | C42: =M42*7 -> 175 | D42: =C42/L42 -> 7 | E42: =M42*15 -> 375 | F42: =E42/L42 -> 15 | G42: =M42*25 -> 625 | H42: =G42/L42 -> 25 | I42: =M42*30 -> 750 | J42: =I42/L42 -> 30 | K42: 1 | L42: 25 | M42: =K42*L42 -> 25
A43: COL007 | B43: Colorant Black 0025 | C43: =M43*7 -> 0 | E43: =M43*15 -> 0 | G43: =M43*25 -> 0 | I43: =M43*30 -> 0 | M43: =K43*L43 -> 0
A44: COL008 | B44: Colorant Blue#5 | C44: =M44*7 -> 0 | E44: =M44*15 -> 0 | G44: =M44*25 -> 0 | I44: =M44*30 -> 0 | M44: =K44*L44 -> 0
A45: COL009 | B45: Colorant Bluish White | C45: =M45*7 -> 0 | E45: =M45*15 -> 0 | G45: =M45*25 -> 0 | I45: =M45*30 -> 0 | M45: =K45*L45 -> 0
A46: COL010 | B46: Colorant Green 726 | C46: =M46*7 -> 0 | E46: =M46*15 -> 0 | G46: =M46*25 -> 0 | I46: =M46*30 -> 0 | M46: =K46*L46 -> 0
A47: COL011 | B47: Colorant Orange 30806 | C47: =M47*7 -> 0 | E47: =M47*15 -> 0 | G47: =M47*25 -> 0 | I47: =M47*30 -> 0 | M47: =K47*L47 -> 0
A48: COL012 | B48: Colorant Pink | C48: =M48*7 -> 0 | E48: =M48*15 -> 0 | G48: =M48*25 -> 0 | I48: =M48*30 -> 0 | M48: =K48*L48 -> 0
A49: COL013 | B49: Colorant Red M100L | C49: =M49*7 -> 0 | E49: =M49*15 -> 0 | G49: =M49*25 -> 0 | I49: =M49*30 -> 0 | M49: =K49*L49 -> 0
A50: COL014 | B50: Colorant Yellow 120 | C50: =M50*7 -> 0 | E50: =M50*15 -> 0 | G50: =M50*25 -> 0 | I50: =M50*30 -> 0 | M50: =K50*L50 -> 0
A51: R103 | B51: PET Bottle Pre-Formed 12g (30mm) | C51: =M51*7 -> 280000 | D51: =C51/L51 -> 280 | E51: =M51*15 -> 600000 | F51: =E51/L51 -> 600 | G51: =M51*25 -> 1000000 | H51: =G51/L51 -> 1000 | I51: =M51*30 -> 1200000 | J51: =I51/L51 -> 1200 | K51: 40 | L51: 1000 | M51: =K51*L51 -> 40000
A52: R104 | B52: PET Bottle Pre-Formed 12g (26mm) (Rgmc) | C52: =M52*7 -> 0 | E52: =M52*15 -> 0 | G52: =M52*25 -> 0 | I52: =M52*30 -> 0 | M52: =K52*L52 -> 0
A53: R105 | B53: PET Bottle Pre-Formed 22g (30mm) | C53: =M53*7 -> 84000 | D53: =C53/L53 -> 140 | E53: =M53*15 -> 180000 | F53: =E53/L53 -> 300 | G53: =M53*25 -> 300000 | H53: =G53/L53 -> 500 | I53: =M53*30 -> 360000 | J53: =I53/L53 -> 600 | K53: 20 | L53: 600 | M53: =K53*L53 -> 12000
A54: R107 | B54: Peanut Jar Clear Pre-Formed 25g | C54: =M54*7 -> 50400 | E54: =M54*15 -> 108000 | G54: =M54*25 -> 180000 | I54: =M54*30 -> 216000 | K54: 12 | L54: 600 | M54: =K54*L54 -> 7200
A55: AC001 | B55: Container Outer Cap w/out inner lock (Rgmc) | C55: =M55*7 -> 30800 | D55: =C55/L55 -> 7 | E55: =M55*15 -> 66000 | F55: =E55/L55 -> 15 | G55: =M55*25 -> 110000 | H55: =G55/L55 -> 25 | I55: =M55*30 -> 132000 | J55: =I55/L55 -> 30 | K55: 1 | L55: 4400 | M55: =K55*L55 -> 4400
A56: AC002 | B56: Container Outer Cap w/inner lock | C56: =M56*7 -> 0 | E56: =M56*15 -> 0 | G56: =M56*25 -> 0 | I56: =M56*30 -> 0 | M56: =K56*L56 -> 0
A57: AC003 | B57: Container Inner Cap | C57: =M57*7 -> 15400 | D57: =C57/L57 -> 7 | E57: =M57*15 -> 33000 | F57: =E57/L57 -> 15 | G57: =M57*25 -> 55000 | H57: =G57/L57 -> 25 | I57: =M57*30 -> 66000 | J57: =I57/L57 -> 30 | K57: 1 | L57: 2200 | M57: =K57*L57 -> 2200
A58: AC004 | B58: Water Container Faucet | C58: =M58*7 -> 8400 | D58: =C58/L58 -> 7 | E58: =M58*15 -> 18000 | F58: =E58/L58 -> 15 | G58: =M58*25 -> 30000 | H58: =G58/L58 -> 25 | I58: =M58*30 -> 36000 | J58: =I58/L58 -> 30 | K58: 1 | L58: 1200 | M58: =K58*L58 -> 1200
A59: AC005 | B59: Water Container Small Outer Cap | C59: =M59*7 -> 8400 | D59: =C59/L59 -> 7 | E59: =M59*15 -> 18000 | F59: =E59/L59 -> 15 | G59: =M59*25 -> 30000 | H59: =G59/L59 -> 25 | I59: =M59*30 -> 36000 | J59: =I59/L59 -> 30 | K59: 1 | L59: 1200 | M59: =K59*L59 -> 1200
A60: AC006 | B60: Water Container Big Outer Cap w/inner cap | C60: =M60*7 -> 0 | E60: =M60*15 -> 0 | G60: =M60*25 -> 0 | I60: =M60*30 -> 0 | M60: =K60*L60 -> 0
A61: AC007 | B61: Water Container Big Outer Cap w/outinner cap (Rgmc) | C61: =M61*7 -> 8400 | D61: =C61/L61 -> 7 | E61: =M61*15 -> 18000 | F61: =E61/L61 -> 15 | G61: =M61*25 -> 30000 | H61: =G61/L61 -> 25 | I61: =M61*30 -> 36000 | J61: =I61/L61 -> 30 | K61: 1 | L61: 1200 | M61: =K61*L61 -> 1200
A62: AC008 | B62: Water Container Inner Cap | C62: =M62*7 -> 4200 | D62: =C62/L62 -> 7 | E62: =M62*15 -> 9000 | F62: =E62/L62 -> 15 | G62: =M62*25 -> 15000 | H62: =G62/L62 -> 25 | I62: =M62*30 -> 18000 | J62: =I62/L62 -> 30 | K62: 1 | L62: 600 | M62: =K62*L62 -> 600
A63: AC009 | B63: PET Bottle Cap Blue 30mm | C63: =M63*7 -> 0 | E63: =M63*15 -> 0 | G63: =M63*25 -> 0 | I63: =M63*30 -> 0 | M63: =K63*L63 -> 0
A64: AC010 | B64: PET Bottle Cap Blue 25mm (Rgmc) | C64: =M64*7 -> 0 | E64: =M64*15 -> 0 | G64: =M64*25 -> 0 | I64: =M64*30 -> 0 | M64: =K64*L64 -> 0
A65: AC011 | B65: PET Bottle Cap Green 30mm | C65: =M65*7 -> 0 | E65: =M65*15 -> 0 | G65: =M65*25 -> 0 | I65: =M65*30 -> 0 | M65: =K65*L65 -> 0
A66: AC012 | B66: PET Bottle Cap Green 25mm (Rgmc) | C66: =M66*7 -> 0 | E66: =M66*15 -> 0 | G66: =M66*25 -> 0 | I66: =M66*30 -> 0 | M66: =K66*L66 -> 0
A67: AC013 | B67: PET Bottle Cap White 30mm | C67: =M67*7 -> 168000 | D67: =C67/L67 -> 56 | E67: =M67*15 -> 360000 | F67: =E67/L67 -> 120 | G67: =M67*25 -> 600000 | H67: =G67/L67 -> 200 | I67: =M67*30 -> 720000 | J67: =I67/L67 -> 240 | K67: 8 | L67: 3000 | M67: =K67*L67 -> 24000
A68: AC014 | B68: PET Bottle Cap White 25mm (Rgmc) | C68: =M68*7 -> 0 | E68: =M68*15 -> 0 | G68: =M68*25 -> 0 | I68: =M68*30 -> 0 | M68: =K68*L68 -> 0
A69: AC015 | B69: White Clear Peanut Jar Cap | C69: =M69*7 -> 28000 | D69: =C69/L69 -> 35 | E69: =M69*15 -> 60000 | F69: =E69/L69 -> 75 | G69: =M69*25 -> 100000 | H69: =G69/L69 -> 125 | I69: =M69*30 -> 120000 | J69: =I69/L69 -> 150 | K69: 5 | L69: 800 | M69: =K69*L69 -> 4000
A70: AC016 | B70: Yellow Clear Peanut Jar Cap | C70: =M70*7 -> 28000 | D70: =C70/L70 -> 35 | E70: =M70*15 -> 60000 | F70: =E70/L70 -> 75 | G70: =M70*25 -> 100000 | H70: =G70/L70 -> 125 | I70: =M70*30 -> 120000 | J70: =I70/L70 -> 150 | K70: 5 | L70: 800 | M70: =K70*L70 -> 4000
A71: AC017 | B71: PET Gallon T-Cap | C71: =M71*7 -> 0 | E71: =M71*15 -> 0 | G71: =M71*25 -> 0 | I71: =M71*30 -> 0 | M71: =K71*L71 -> 0
A72: AC018 | B72: Gallon Cap | C72: =M72*7 -> 0 | E72: =M72*15 -> 0 | G72: =M72*25 -> 0 | I72: =M72*30 -> 0 | M72: =K72*L72 -> 0
A73: AC019 | B73: Gallon Plastic Seal | C73: =M73*7 -> 0 | E73: =M73*15 -> 0 | G73: =M73*25 -> 0 | I73: =M73*30 -> 0 | M73: =K73*L73 -> 0
A74: AC020 | B74: Gallon Styro Liner | C74: =M74*7 -> 0 | E74: =M74*15 -> 0 | G74: =M74*25 -> 0 | I74: =M74*30 -> 0 | M74: =K74*L74 -> 0
A75: AC021 | B75: Peanut Jar Cap 50mm (small) | C75: =M75*7 -> 168000 | D75: =C75/L75 -> 112 | E75: =M75*15 -> 360000 | F75: =E75/L75 -> 240 | G75: =M75*25 -> 600000 | H75: =G75/L75 -> 400 | I75: =M75*30 -> 720000 | J75: =I75/L75 -> 480 | K75: 16 | L75: 1500 | M75: =K75*L75 -> 24000
A76: AC022 | B76: Peanut Jar Cap 67mm (med/large) | C76: =M76*7 -> 112000 | D76: =C76/L76 -> 140 | E76: =M76*15 -> 240000 | F76: =E76/L76 -> 300 | G76: =M76*25 -> 400000 | H76: =G76/L76 -> 500 | I76: =M76*30 -> 480000 | J76: =I76/L76 -> 600 | K76: 20 | L76: 800 | M76: =K76*L76 -> 16000
A77: AC023 | B77: Sago Straw Paper Wrap | C77: =M77*7 -> 0 | E77: =M77*15 -> 0 | G77: =M77*25 -> 0 | I77: =M77*30 -> 0 | M77: =K77*L77 -> 0
A78: AC024 | B78: Plastic Twine | C78: =M78*7 -> 280 | D78: =C78/L78 -> 280 | E78: =M78*15 -> 600 | F78: =E78/L78 -> 600 | G78: =M78*25 -> 1000 | H78: =G78/L78 -> 1000 | I78: =M78*30 -> 1200 | J78: =I78/L78 -> 1200 | K78: 40 | L78: 1 | M78: =K78*L78 -> 40
A79: AC025 | B79: Plastic Strapping | C79: =M79*7 -> 14 | D79: =C79/L79 -> 14 | E79: =M79*15 -> 30 | F79: =E79/L79 -> 30 | G79: =M79*25 -> 50 | H79: =G79/L79 -> 50 | I79: =M79*30 -> 60 | J79: =I79/L79 -> 60 | K79: 2 | L79: 1 | M79: =K79*L79 -> 2
A80: AC026 | B80: Sack 28x50 | C80: =M80*7 -> 1750 | D80: =C80/L80 -> 1750 | E80: =M80*15 -> 3750 | F80: =E80/L80 -> 3750 | G80: =M80*25 -> 6250 | H80: =G80/L80 -> 6250 | I80: =M80*30 -> 7500 | J80: =I80/L80 -> 7500 | K80: 250 | L80: 1 | M80: =K80*L80 -> 250
A81: AC028 | B81: Packaging Tape 2" | C81: =M81*7 -> 420 | D81: =C81/L81 -> 420 | E81: =M81*15 -> 900 | F81: =E81/L81 -> 900 | G81: =M81*25 -> 1500 | H81: =G81/L81 -> 1500 | I81: =M81*30 -> 1800 | J81: =I81/L81 -> 1800 | K81: 60 | L81: 1 | M81: =K81*L81 -> 60
A82: AC029 | B82: Packaging Tape 1/2" | C82: =M82*7 -> 560 | D82: =C82/L82 -> 560 | E82: =M82*15 -> 1200 | F82: =E82/L82 -> 1200 | G82: =M82*25 -> 2000 | H82: =G82/L82 -> 2000 | I82: =M82*30 -> 2400 | J82: =I82/L82 -> 2400 | K82: 80 | L82: 1 | M82: =K82*L82 -> 80
A83: AC101 | B83: Paint Black | C83: =M83*7 -> 0 | E83: =M83*15 -> 0 | G83: =M83*25 -> 0 | I83: =M83*30 -> 0 | M83: =K83*L83 -> 0
A84: AC102 | B84: Paint Blue | C84: =M84*7 -> 0 | E84: =M84*15 -> 0 | G84: =M84*25 -> 0 | I84: =M84*30 -> 0 | M84: =K84*L84 -> 0
A85: AC103 | B85: Paint Green | C85: =M85*7 -> 0 | E85: =M85*15 -> 0 | G85: =M85*25 -> 0 | I85: =M85*30 -> 0 | M85: =K85*L85 -> 0
A86: AC104 | B86: Paint Red | C86: =M86*7 -> 0 | E86: =M86*15 -> 0 | G86: =M86*25 -> 0 | I86: =M86*30 -> 0 | M86: =K86*L86 -> 0
A87: AC105 | B87: Paint White | C87: =M87*7 -> 0 | E87: =M87*15 -> 0 | G87: =M87*25 -> 0 | I87: =M87*30 -> 0 | M87: =K87*L87 -> 0
A88: AC106 | B88: Paint Yellow | C88: =M88*7 -> 0 | E88: =M88*15 -> 0 | G88: =M88*25 -> 0 | I88: =M88*30 -> 0 | M88: =K88*L88 -> 0
A89: AC107 | B89: Solvent | C89: =M89*7 -> 0 | E89: =M89*15 -> 0 | G89: =M89*25 -> 0 | I89: =M89*30 -> 0 | M89: =K89*L89 -> 0
A90: AC108 | B90: Paint Pink | C90: =M90*7 -> 0 | E90: =M90*15 -> 0 | G90: =M90*25 -> 0 | I90: =M90*30 -> 0 | M90: =K90*L90 -> 0
A91: AC109 | B91: Paint Violet | C91: =M91*7 -> 0 | E91: =M91*15 -> 0 | G91: =M91*25 -> 0 | I91: =M91*30 -> 0 | M91: =K91*L91 -> 0
A92: AC110 | B92: Paint Orange | C92: =M92*7 -> 0 | E92: =M92*15 -> 0 | G92: =M92*25 -> 0 | I92: =M92*30 -> 0 | M92: =K92*L92 -> 0
A93: AC111 | B93: Plastic Twine Virgin (pcs) | C93: =M93*7 -> 0 | E93: =M93*15 -> 0 | G93: =M93*25 -> 0 | I93: =M93*30 -> 0 | M93: =K93*L93 -> 0
A94: AC112 | B94: Clarifying Agent (bags) | C94: =M94*7 -> 0 | E94: =M94*15 -> 0 | G94: =M94*25 -> 0 | I94: =M94*30 -> 0 | M94: =K94*L94 -> 0

Sheet High Low Inv New
B2: ='RM Rollforward'!B3 -> As of June 20, 2025
A3: SKU | B3: Description | C3: Qty. Status | D3: High | E3: Inv in Kg & Pcs | F3: Ave. Daily Consuption | G3: Inv in Kilo | H3: Price | I3: Total Cost Inv | J3: Conversion to Kg | K3: OPEN PO | L3: Incoming | M3: FOR ORDER | N3: Total
A4: AC013 | B4: PET Bottle Cap White 30mm | C4: =if(E4<=168000,"Critical",IF(E4<=360000,"Low",IF(E4<=600000,"Moderate",IF(E4<=720000,"High")))) -> Critical | D4: 900000 | E4: ='RM Rollforward'!H62 -> 0 | K4: 360000 | M4: =D4-E4-L4 -> 900000 | N4: =E4+L4 -> 0 | O4: =N4-D4 -> -900000
A5: AC014 | B5: PET Bottle Cap White 25mm (RGMC) | C5: =if(E5<=168000,"Critical",IF(E5<=360000,"Low",IF(E5<=600000,"Moderate",IF(E5<=720000,"High")))) -> Critical | D5: 0 | E5: ='RM Rollforward'!H63 -> 0 | G5: =E5*J5 -> 0 | H5: ='RM Rollforward'!J86 -> 150 | I5: ='RM Rollforward'!L86 -> 38100 | K5: 0 | M5: =D5-E5-L5 -> 0 | N5: =E5+L5 -> 0 | O5: =N5-D5 -> 0
A6: R001 | B6: HDPE Blue | C6: =if(E6<=11000,"Critical",IF(E6<=23000,"Low",IF(E6<=38000,"Moderate",IF(E6<=45000,"High")))) -> Critical | D6: 35000 | E6: ='RM Rollforward'!H7 -> 6590 | G6: =E6*J6 -> 0 | H6: ='RM Rollforward'!J93 -> 150 | I6: ='RM Rollforward'!L93 -> 30450 | K6: 27350 | M6: =D6-E6-L6 -> 28410 | N6: =E6+L6 -> 6590 | O6: =N6-D6 -> -28410
A7: R002 | B7: HDPE Red | C7: =if(E7<=11000,"Critical",IF(E7<=23000,"Low",IF(E7<=38000,"Moderate",IF(E7<=45000,"High")))) -> Critical | D7: 35000 | E7: ='RM Rollforward'!H8 -> 3000 | G7: =E7*J7 -> 0 | H7: ='RM Rollforward'!J52 -> 3.1 | I7: ='RM Rollforward'!L52 -> 837000 | K7: 6000 | M7: =D7-E7-L7 -> 32000 | N7: =E7+L7 -> 3000 | O7: =N7-D7 -> -32000
A8: R003 | B8: HDPE Green | C8: =if(E8<=11000,"Critical",IF(E8<=23000,"Low",IF(E8<=38000,"Moderate",IF(E8<=45000,"High")))) -> Critical | D8: 35000 | E8: ='RM Rollforward'!H9 -> 0 | G8: =E8*J8 -> 0 | H8: ='RM Rollforward'!J25 -> 75 | I8: ='RM Rollforward'!L25 -> 0 | K8: 900 | M8: =D8-E8-L8 -> 35000 | N8: =E8+L8 -> 0 | O8: =N8-D8 -> -35000
A9: R004 | B9: HDPE Black | C9: =if(E9<=40000,"Critical",IF(E9<=80000,"Low",IF(E9<=100000,"Moderate",IF(E9<=145000,"High")))) -> Critical | D9: 35000 | E9: ='RM Rollforward'!H10 -> 22715 | G9: =E9*J9 -> 0 | H9: ='RM Rollforward'!J72 -> 1200 | I9: ='RM Rollforward'!L72 -> 140400 | K9: 56355 | M9: =D9-E9-L9 -> 12285 | N9: =E9+L9 -> 22715 | O9: =N9-D9 -> -12285
A10: COL012 | B10: Colorant Pink | C10: =if(E10<=175,"Critical",IF(E10<=375,"Low",IF(E10<=625,"Moderate",IF(E10<=750,"High")))) -> Critical | E10: ='RM Rollforward'!H47 -> 100 | F10: 40 | G10: =E10*J10 -> 100000 | H10: ='RM Rollforward'!J53 -> 2.4 | I10: ='RM Rollforward'!L53 -> 324000 | J10: 1000 | K10: =919+25 -> 944 | M10: =D10-E10-L10 -> -100 | N10: =E10+L10 -> 100 | O10: =N10-D10 -> 100
A11: R005 | B11: HDPE White | C11: =if(E11<=11000,"Critical",IF(E11<=23000,"Low",IF(E11<=38000,"Moderate",IF(E11<=45000,"High")))) -> Critical | D11: 35000 | E11: ='RM Rollforward'!H11 -> 4685 | G11: =E11*J11 -> 0 | H11: ='RM Rollforward'!J74 -> 39 | I11: ='RM Rollforward'!L74 -> 22932 | K11: 9090 | M11: =D11-E11-L11 -> 30315 | N11: =E11+L11 -> 4685 | O11: =N11-D11 -> -30315
A12: R006 | B12: HDPE Yellow | C12: =if(E12<=11000,"Critical",IF(E12<=23000,"Low",IF(E12<=38000,"Moderate",IF(E12<=45000,"High")))) -> Critical | D12: 35000 | E12: ='RM Rollforward'!H12 -> 0 | F12: 160 | G12: =E12*J12 -> 0 | H12: 42 | I12: =SUM('RM Rollforward'!L13:L14) -> 1503437.5 | J12: 30 | K12: 600 | M12: =D12-E12-L12 -> 35000 | N12: =E12+L12 -> 0 | O12: =N12-D12 -> -35000
A13: R007 | B13: HDPE Orange | C13: =if(E13<=11000,"Critical",IF(E13<=23000,"Low",IF(E13<=38000,"Moderate",IF(E13<=45000,"High")))) -> Critical | D13: 0 | E13: ='RM Rollforward'!H13 -> 25 | F13: 50 | G13: =E13*J13 -> 625 | H13: ='RM Rollforward'!J7 -> 45 | I13: =SUM('RM Rollforward'!L7:L8) -> 431550 | J13: 25 | K13: 0 | M13: =D13-E13-L13 -> -25 | N13: =E13+L13 -> 25 | O13: =N13-D13 -> 25
A14: R019 | B14: PP Recycle Transparent | C14: =if(E14<=5000,"Critical",IF(E14<=11000,"Low",IF(E14<=18000,"Moderate",IF(E14<=21000,"High")))) -> Critical | D14: 21000 | E14: ='RM Rollforward'!H22 -> 0 | G14: =E14*J14 -> 0 | H14: ='RM Rollforward'!J32 -> 74 | I14: ='RM Rollforward'!L32 -> 185000 | K14: 0 | M14: =D14-E14-L14 -> 21000 | N14: =E14+L14 -> 0 | O14: =N14-D14 -> -21000
A15: R103 | B15: PET Bottle Pre-Formed 12g (30mm) | C15: =if(E15<=280000,"Critical",IF(E15<=600000,"Low",IF(E15<=1000000,"Moderate",IF(E15<=1200000,"High")))) -> Critical | D15: 900000 | E15: ='RM Rollforward'!H48 -> 0 | F15: 20 | G15: =E15*J15 -> 0 | H15: ='RM Rollforward'!J55 -> 9 | I15: ='RM Rollforward'!L55 -> 367200 | J15: 600 | K15: 69000 | M15: =D15-E15-L15 -> 900000 | N15: =E15+L15 -> 0 | O15: =N15-D15 -> -900000
A16: R104 | B16: PET Bottle Pre-Formed 12g (26mm) (RGMC) | C16: =if(E16<=280000,"Critical",IF(E16<=600000,"Low",IF(E16<=1000000,"Moderate",IF(E16<=1200000,"High")))) -> Critical | D16: 0 | E16: ='RM Rollforward'!H49 -> 33000 | G16: =E16*J16 -> 36300000 | H16: ='RM Rollforward'!J40 -> 241 | I16: ='RM Rollforward'!L40 -> 384877 | J16: 1100 | K16: 0 | M16: =D16-E16-L16 -> -33000 | N16: =E16+L16 -> 33000 | O16: =N16-D16 -> 33000
A17: R105 | B17: PET Bottle Pre-Formed 22g (30mm) | C17: =if(E17<=84000,"Critical",IF(E17<=180000,"Low",IF(E17<=300000,"Moderate",IF(E17<=360000,"High")))) -> Critical | D17: 200000 | E17: ='RM Rollforward'!H50 -> 0 | G17: =E17*J17 -> 0 | H17: ='RM Rollforward'!J92 -> 150 | I17: ='RM Rollforward'!L92 -> 1350 | K17: 254400 | M17: =D17-E17-L17 -> 200000 | N17: =E17+L17 -> 0 | O17: =N17-D17 -> -200000
A18: AC107 | B18: Packaging Tape 1/2" | C18: =if(E18<=560,"Critical",IF(E18<=1200,"Low",IF(E18<=2000,"Moderate",IF(E18<=2400,"High")))) -> Low | D18: 0 | E18: ='RM Rollforward'!H75 -> 633 | F18: 1 | G18: =E18*J18 -> 759600 | H18: ='RM Rollforward'!J60 -> 0.3 | I18: ='RM Rollforward'!L60 -> 27000 | J18: 1200 | M18: =D18-E18-L18 -> -633 | N18: =E18+L18 -> 633 | O18: =N18-D18 -> 633
A19: R009 | B19: HDPE Film Virgin | C19: =if(E19<=27000,"Critical",IF(E19<=57000,"Low",IF(E19<=94000,"Moderate",IF(E19<=113000,"High")))) -> Critical | D19: 87500 | E19: ='RM Rollforward'!H15 -> 1825 | F19: 50 | G19: =E19*J19 -> 54750 | H19: ='RM Rollforward'!J11 -> 48 | I19: =SUM('RM Rollforward'!L11:L12) -> 224880 | J19: 30 | K19: 55000 | M19: =D19-E19-L19 -> 85675 | N19: =E19+L19 -> 1825 | O19: =N19-D19 -> -85675
A20: AC101 | B20: Plastic Twine | C20: =if(E20<=280,"Critical",IF(E20<=600,"Low",IF(E20<=1000,"Moderate",IF(E20<=1200,"High")))) -> High | D20: 1200 | E20: ='RM Rollforward'!H70 -> 1058 | F20: 1 | G20: =E20*J20 -> 26450 | H20: ='RM Rollforward'!J45 -> 130 | I20: ='RM Rollforward'!L45 -> 42250 | J20: 25 | K20: 0 | M20: =D20-E20-L20 -> 142 | N20: =E20+L20 -> 1058 | O20: =N20-D20 -> -142
A21: R016 | B21: PP Yarn Virgin | C21: =if(E21<=19000,"Critical",IF(E21<=40000,"Low",IF(E21<=67000,"Moderate",IF(E21<=80000,"High")))) -> Critical | D21: 79500 | E21: ='RM Rollforward'!H20 -> 10300 | G21: =E21*J21 -> 0 | H21: ='RM Rollforward'!J30 -> 75 | I21: ='RM Rollforward'!L30 -> 303750 | K21: 87500 | M21: =D21-E21-L21 -> 69200 | N21: =E21+L21 -> 10300 | O21: =N21-D21 -> -69200
A22: R029 | B22: PP Injection Virgin | C22: =if(E22<=500,"Critical",IF(E22<=1000,"Low",IF(E22<=1500,"Moderate",IF(E22<=2500,"High")))) -> High | D22: 2500 | E22: ='RM Rollforward'!H32 -> 2500 | G22: =E22*J22 -> 0 | H22: ='RM Rollforward'!J33 -> 42 | I22: ='RM Rollforward'!L33 -> 0 | K22: 2500 | M22: =D22-E22-L22 -> 0 | N22: =E22+L22 -> 2500 | O22: =N22-D22 -> 0
A23: R031 | B23: PET Resin | C23: =if(E23<=1100,"Critical",IF(E23<=2200,"Low",IF(E23<=3300,"Moderate",IF(E23<=5500,"High")))) -> High | D23: 5500 | E23: ='RM Rollforward'!H34 -> 4400 | G23: =E23*J23 -> 0 | H23: ='RM Rollforward'!J35 -> 76 | I23: ='RM Rollforward'!L35 -> 286900 | K23: 0 | M23: =D23-E23-L23 -> 1100 | N23: =E23+L23 -> 4400 | O23: =N23-D23 -> -1100
A24: AC005 | B24: Water Container Small Outer Cap | C24: =if(E24<=10500,"Critical",IF(E24<=21000,"Low",IF(E24<=63000,"Moderate",IF(E24<=120000,"High")))) -> High | D24: 80000 | E24: ='RM Rollforward'!H56 -> 73500 | G24: =E24*J24 -> 0 | H24: ='RM Rollforward'!J64 -> 0.75 | I24: ='RM Rollforward'!L64 -> 201600 | K24: 0 | M24: =D24-E24-L24 -> 6500 | N24: =E24+L24 -> 73500 | O24: =N24-D24 -> -6500
A25: AC110 | B25: Paint Blue | C25: =if(E25<=10,"Critical",IF(E25<=50,"Low",IF(E25<=150,"Moderate",IF(E25<250,"High")))) -> High | D25: 0 | E25: ='RM Rollforward'!H78 -> 180 | K25: 0 | M25: =D25-E25-L25 -> -180 | N25: =E25+L25 -> 180 | O25: =N25-D25 -> 180
A26: AC111 | B26: Paint Green | C26: =if(E26<=10,"Critical",IF(E26<=50,"Low",IF(E26<=150,"Moderate",IF(E26<250,"High")))) -> High | D26: 0 | E26: ='RM Rollforward'!H79 -> 222 | K26: 0 | M26: =D26-E26-L26 -> -222 | N26: =E26+L26 -> 222 | O26: =N26-D26 -> 222
A27: AC114 | B27: Paint Yellow | C27: =if(E27<=10,"Critical",IF(E27<=50,"Low",IF(E27<=150,"Moderate",IF(E27<250,"High")))) -> High | D27: 0 | E27: ='RM Rollforward'!H82 -> 180 | K27: 0 | M27: =D27-E27-L27 -> -180 | N27: =E27+L27 -> 180 | O27: =N27-D27 -> 180
A28: AC115 | B28: Paint Pink | C28: =if(E28<=10,"Critical",IF(E28<=50,"Low",IF(E28<=150,"Moderate",IF(E28<200,"High")))) -> High | D28: 0 | E28: ='RM Rollforward'!H83 -> 170 | K28: 0 | M28: =D28-E28-L28 -> -170 | N28: =E28+L28 -> 170 | O28: =N28-D28 -> 170
A29: R012 | B29: LLDPE Virgin | C29: =if(E29<=3000,"Critical",IF(E29<=6000,"Low",IF(E29<=12000,"Moderate",IF(E29<=30000,"High")))) -> High | D29: 0 | E29: ='RM Rollforward'!H17 -> 24625 | F29: 10 | G29: =E29*J29 -> 615625 | H29: ='RM Rollforward'!J39 -> 201 | I29: ='RM Rollforward'!L39 -> 290244 | J29: 25 | K29: 0 | M29: =D29-E29-L29 -> -24625 | N29: =E29+L29 -> 24625 | O29: =N29-D29 -> 24625
A30: AC003 | B30: Container Inner Cap | C30: =if(E30<=20000,"Critical",IF(E30<=40000,"Low",IF(E30<=60000,"Moderate",IF(E30<=150000,"High")))) -> High | D30: 0 | E30: ='RM Rollforward'!H54 -> 129000 | F30: 1 | G30: =E30*J30 -> 283800000 | H30: ='RM Rollforward'!J58 -> 3.4 | I30: ='RM Rollforward'!L58 -> 39270 | J30: 2200 | K30: 86000 | M30: =D30-E30-L30 -> -129000 | N30: =E30+L30 -> 129000 | O30: =N30-D30 -> 129000
A31: AC002 | B31: Container Outer Cap w/inner lock (RGMC) | C31: =if(E31<=30800,"Critical",IF(E31<=66000,"Low",IF(E31<=110000,"Moderate",IF(E31<=141000,"High")))) -> High | D31: 0 | E31: ='RM Rollforward'!H53 -> 135000 | F31: 28 | G31: =E31*J31 -> 3375000 | H31: ='RM Rollforward'!J28 -> 75 | I31: ='RM Rollforward'!L28 -> 20625 | J31: 25 | K31: 0 | M31: =D31-E31-L31 -> -135000 | N31: =E31+L31 -> 135000 | O31: =N31-D31 -> 135000
A32: AC103 | B32: Plastic Strapping | C32: =if(E32<=20,"Critical",IF(E32<=40,"Low",IF(E32<=80,"Moderate",IF(E32<=200,"High")))) -> High | D32: 70 | E32: ='RM Rollforward'!H72 -> 117 | G32: =E32*J32 -> 0 | H32: ='RM Rollforward'!J88 -> 150 | I32: ='RM Rollforward'!L88 -> 0 | K32: 100 | M32: =D32-E32-L32 -> -47 | N32: =E32+L32 -> 117 | O32: =N32-D32 -> 47
A33: R008 | B33: HDPE Blow Virgin | C33: =if(E33<=6000,"Critical",IF(E33<=13000,"Low",IF(E33<=22000,"Moderate",IF(E33<=26000,"High")))) -> Moderate | D33: 25500 | E33: ='RM Rollforward'!H14 -> 18875 | F33: 150 | G33: =E33*J33 -> 471875 | H33: 75 | I33: ='RM Rollforward'!L21 -> 692250 | J33: 25 | K33: 17500 | L33: 17500 | M33: =D33-E33-L33 -> -10875 | N33: =E33+L33 -> 36375 | O33: =N33-D33 -> 10875
A34: COL001 | B34: SB Colorant D6 Blue | C34: =if(E34<=350,"Critical",IF(E34<=750,"Low",IF(E34<=1250,"Moderate",IF(E34<=1500,"High")))) -> High | D34: 1000 | E34: ='RM Rollforward'!H38 -> 1300 | F34: 50 | G34: =E34*J34 -> 39000 | H34: 48 | I34: =SUM('RM Rollforward'!L15:L16) -> 190162.5 | J34: 30 | K34: 1000 | M34: =D34-E34-L34 -> -300 | N34: =E34+L34 -> 1300 | O34: =N34-D34 -> 300
A35: COL003 | B35: SB Colorant D5 Orange | C35: =if(E35<=200,"Critical",IF(E35<=400,"Low",IF(E35<=800,"Moderate",IF(E35<=2000,"High")))) -> High | D35: 1000 | E35: ='RM Rollforward'!H40 -> 1597 | G35: =E35*J35 -> 0 | H35: ='RM Rollforward'!J22 -> 57 | I35: ='RM Rollforward'!L22 -> 0 | K35: 25 | M35: =D35-E35-L35 -> -597 | N35: =E35+L35 -> 1597 | O35: =N35-D35 -> 597
A36: AC004 | B36: Water Container Faucet | C36: =if(E36<=8400,"Critical",IF(E36<=18000,"Low",IF(E36<=30000,"Moderate",IF(E36<=60000,"High")))) -> High | D36: 40000 | E36: ='RM Rollforward'!H55 -> 40800 | G36: =E36*J36 -> 0 | H36: ='RM Rollforward'!J56 -> 0.6 | I36: ='RM Rollforward'!L56 -> 44100 | K36: 60000 | M36: =D36-E36-L36 -> -800 | N36: =E36+L36 -> 40800 | O36: =N36-D36 -> 800
A37: AC021 | B37: Peanut Jar Cap 50mm (Small) | C37: =if(E37<=168000,"Critical",IF(E37<=360000,"Low",IF(E37<=600000,"Moderate",IF(E37<=1000000,"High")))) -> High | D37: 720000 | E37: ='RM Rollforward'!H68 -> 897000 | G37: =E37*J37 -> 0 | H37: ='RM Rollforward'!J29 -> 75 | I37: ='RM Rollforward'!L29 -> 511875 | K37: 394000 | M37: =D37-E37-L37 -> -177000 | N37: =E37+L37 -> 897000 | O37: =N37-D37 -> 177000
A38: COL002 | B38: SB Colorant D4 Green | C38: =if(E38<=175,"Critical",IF(E38<=375,"Low",IF(E38<=625,"Moderate",IF(E38<=2000,"High")))) -> High | D38: 750 | E38: ='RM Rollforward'!H39 -> 1444 | F38: 10 | G38: =E38*J38 -> 43320 | H38: ='RM Rollforward'!J24 -> 75 | I38: ='RM Rollforward'!L24 -> 75000 | J38: 30 | K38: 1000 | M38: =D38-E38-L38 -> -694 | N38: =E38+L38 -> 1444 | O38: =N38-D38 -> 694
A39: COL004 | B39: SB Colorant D8 Red | C39: =if(E39<=350,"Critical",IF(E39<=750,"Low",IF(E39<=1250,"Moderate",IF(E39<=2000,"High")))) -> High | D39: 1000 | E39: ='RM Rollforward'!H41 -> 1625 | F39: 16 | G39: =E39*J39 -> 2437500 | H39: ='RM Rollforward'!J75 -> 10 | I39: ='RM Rollforward'!L75 -> 6330 | J39: 1500 | K39: 1000 | M39: =D39-E39-L39 -> -625 | N39: =E39+L39 -> 1625 | O39: =N39-D39 -> 625
A40: AC007 | B40: Water Container Big Outer Cap w/outinner cap | C40: =if(E40<=8400,"Critical",IF(E40<=18000,"Low",IF(E40<=30000,"Moderate",IF(E40<=36000,"High")))) -> Low | D40: 0 | E40: ='RM Rollforward'!H58 -> 11550 | F40: 2 | G40: =E40*J40 -> 11550 | H40: ='RM Rollforward'!J78 -> 300 | I40: ='RM Rollforward'!L78 -> 54000 | J40: 1 | K40: 0 | M40: =D40-E40-L40 -> -11550 | N40: =E40+L40 -> 11550 | O40: =N40-D40 -> 11550
A41: COL008 | B41: Colorant Blue#5 | C41: =if(E41<=175,"Critical",IF(E41<=375,"Low",IF(E41<=625,"Moderate",IF(E41<=750,"High")))) -> Low | D41: 500 | E41: ='RM Rollforward'!H45 -> 325 | G41: =E41*J41 -> 0 | H41: ='RM Rollforward'!J69 -> 0.7 | I41: ='RM Rollforward'!L69 -> 269920 | K41: 0 | M41: =D41-E41-L41 -> 175 | N41: =E41+L41 -> 325 | O41: =N41-D41 -> -175
A42: R013 | B42: LDPE Recycle | C42: =if(E42<=2200,"Critical",IF(E42<=5000,"Low",IF(E42<=7500,"Moderate",IF(E42<=9000,"High")))) -> Critical | D42: 9000 | E42: ='RM Rollforward'!H18 -> 900 | F42: 20 | G42: =E42*J42 -> 22500 | H42: ='RM Rollforward'!J41 -> 188 | I42: ='RM Rollforward'!L41 -> 305500 | J42: 25 | K42: 0 | M42: =D42-E42-L42 -> 8100 | N42: =E42+L42 -> 900 | O42: =N42-D42 -> -8100
A43: R015 | B43: Dehydrating Agent | C43: =if(E43<=600,"Critical",IF(E43<=1200,"Low",IF(E43<=2400,"Moderate",IF(E43<=4800,"High")))) -> Critical | D43: 2500 | E43: ='RM Rollforward'!H19 -> 300 | G43: =E43*J43 -> 0 | H43: 45 | I43: =SUM('RM Rollforward'!L19) -> 15000 | K43: 0 | M43: =D43-E43-L43 -> 2200 | N43: =E43+L43 -> 300 | O43: =N43-D43 -> -2200
A44: AC116 | B44: Paint Violet | C44: =if(E44<=10,"Critical",IF(E44<=50,"Low",IF(E44<=150,"Moderate",IF(E44<200,"High")))) -> Low | D44: 0 | E44: ='RM Rollforward'!H84 -> 50 | K44: 0 | M44: =D44-E44-L44 -> -50 | N44: =E44+L44 -> 50 | O44: =N44-D44 -> 50
A45: AC106 | B45: Packaging Tape 2" | C45: =if(E45<=420,"Critical",IF(E45<=900,"Low",IF(E45<=1500,"Moderate",IF(E45<=1800,"High")))) -> Low | E45: ='RM Rollforward'!H74 -> 588 | F45: 1 | G45: =E45*J45 -> 705600 | H45: ='RM Rollforward'!J62 -> 0.3 | I45: ='RM Rollforward'!L62 -> 0 | J45: 1200 | K45: 0 | M45: =D45-E45-L45 -> -588 | N45: =E45+L45 -> 588 | O45: =N45-D45 -> 588
A46: R018 | B46: PP Film Virgin | C46: =if(E46<=7000,"Critical",IF(E46<=15000,"Low",IF(E46<=18000,"Moderate",IF(E46<=30000,"High")))) -> Low | D46: 30000 | E46: ='RM Rollforward'!H21 -> 9750 | G46: =E46*J46 -> 0 | H46: ='RM Rollforward'!J31 -> 75 | I46: ='RM Rollforward'!L31 -> 15000 | K46: 0 | M46: =D46-E46-L46 -> 20250 | N46: =E46+L46 -> 9750 | O46: =N46-D46 -> -20250
A47: AC104 | B47: Sack 28x50 | C47: =if(E47<=1750,"Critical",IF(E47<=3750,"Low",IF(E47<=6250,"Moderate",IF(E47<=7500,"High")))) -> Low | D47: 7500 | E47: ='RM Rollforward'!H73 -> 2445 | G47: =E47*J47 -> 0 | H47: ='RM Rollforward'!J61 -> 0.3 | I47: ='RM Rollforward'!L61 -> 59400 | K47: 0 | M47: =D47-E47-L47 -> 5055 | N47: =E47+L47 -> 2445 | O47: =N47-D47 -> -5055
A48: COL009 | B48: Colorant Bluish White | C48: =if(E48<=175,"Critical",IF(E48<=375,"Low",IF(E48<=625,"Moderate",IF(E48<=750,"High")))) -> Low | D48: 750 | E48: ='RM Rollforward'!H46 -> 375 | G48: =E48*J48 -> 0 | H48: ='RM Rollforward'!J54 -> 0.6 | I48: ='RM Rollforward'!L54 -> 77400 | K48: 0 | M48: =D48-E48-L48 -> 375 | N48: =E48+L48 -> 375 | O48: =N48-D48 -> -375
A49: R032 | B49: HDPE Injection | C49: =if(E49<=500,"Critical",IF(E49<=1000,"Low",IF(E49<=2000,"Moderate",IF(E49<=5000,"High")))) -> High | D49: 0 | E49: ='RM Rollforward'!H35 -> 3775 | G49: =E49*J49 -> 0 | H49: ='RM Rollforward'!J36 -> 74 | I49: ='RM Rollforward'!L36 -> 88800 | K49: 0 | M49: =D49-E49-L49 -> -3775 | N49: =E49+L49 -> 3775 | O49: =N49-D49 -> 3775
A50: COL006 | B50: SB Colorant D7 Yellow | C50: =if(E50<=350,"Critical",IF(E50<=750,"Low",IF(E50<=1250,"Moderate",IF(E50<=1500,"High")))) -> Moderate | D50: 750 | E50: ='RM Rollforward'!H43 -> 1095 | G50: =E50*J50 -> 0 | H50: ='RM Rollforward'!J67 -> 0.55 | I50: ='RM Rollforward'!L67 -> 0 | K50: 750 | M50: =D50-E50-L50 -> -345 | N50: =E50+L50 -> 1095 | O50: =N50-D50 -> 345
A51: AC112 | B51: Paint Red | C51: =if(E51<=10,"Critical",IF(E51<=50,"Low",IF(E51<=150,"Moderate",IF(E51<200,"High")))) -> Moderate | D51: 0 | E51: ='RM Rollforward'!H80 -> 120 | K51: 0 | M51: =D51-E51-L51 -> -120 | N51: =E51+L51 -> 120 | O51: =N51-D51 -> 120
A52: AC022 | B52: Peanut Jar Cap 67mm (Medium) | C52: =if(E52<=112000,"Critical",IF(E52<=240000,"Low",IF(E52<=400000,"Moderate",IF(E52<=480000,"High")))) -> Moderate | D52: 480000 | E52: ='RM Rollforward'!H69 -> 385600 | F52: 1 | G52: =E52*J52 -> 9640000 | H52: ='RM Rollforward'!J44 -> 84 | I52: ='RM Rollforward'!L44 -> 90216 | J52: 25 | K52: 352800 | M52: =D52-E52-L52 -> 94400 | N52: =E52+L52 -> 385600 | O52: =N52-D52 -> -94400
A53: COL005 | B53: SB Colorant 116 White | C53: =if(E53<=350,"Critical",IF(E53<=750,"Low",IF(E53<=1250,"Moderate",IF(E53<=1500,"High")))) -> Moderate | D53: 1000 | E53: ='RM Rollforward'!H42 -> 925 | G53: =E53*J53 -> 0 | H53: ='RM Rollforward'!J65 -> 0.9 | I53: ='RM Rollforward'!L65 -> 216000 | K53: 1000 | M53: =D53-E53-L53 -> 75 | N53: =E53+L53 -> 925 | O53: =N53-D53 -> -75
A54: COL007 | B54: Colorant Black 0025 | C54: =if(E54<=350,"Critical",IF(E54<=750,"Low",IF(E54<=1250,"Moderate",IF(E54<=1500,"High")))) -> Moderate | D54: 1000 | E54: ='RM Rollforward'!H44 -> 1074 | F54: 20 | G54: =E54*J54 -> 859200 | H54: ='RM Rollforward'!J76 -> 95 | I54: ='RM Rollforward'!L76 -> 104500 | J54: 800 | K54: 1000 | M54: =D54-E54-L54 -> -74 | N54: =E54+L54 -> 1074 | O54: =N54-D54 -> 74
A55: AC108 | B55: Solvent | C55: =if(E55<=400,"Critical",IF(E55<=800,"Low",IF(E55<=1600,"Moderate",IF(E55<=3200,"High")))) -> Moderate | D55: 2000 | E55: ='RM Rollforward'!H76 -> 1100 | K55: 0 | M55: =D55-E55-L55 -> 900 | N55: =E55+L55 -> 1100 | O55: =N55-D55 -> -900
A56: AC006 | B56: Water Container Big Outer Cap w/inner cap (RGMC) | C56: =if(E56<=20000,"Critical",IF(E56<=50000,"Low",IF(E56<=75000,"Moderate",IF(E56<=100000,"High")))) -> Moderate | D56: 0 | E56: ='RM Rollforward'!H57 -> 54200 | G56: =E56*J56 -> 0 | H56: ='RM Rollforward'!J66 -> 0.11 | I56: ='RM Rollforward'!L66 -> 1100 | K56: 0 | M56: =D56-E56-L56 -> -54200 | N56: =E56+L56 -> 54200 | O56: =N56-D56 -> 54200
A57: AC008 | B57: Water Container Inner Cap | C57: =if(E57<=4200,"Critical",IF(E57<=9000,"Low",IF(E57<=15000,"Moderate",IF(E57<=18000,"High")))) -> Moderate | D57: 80000 | E57: ='RM Rollforward'!H59 -> 9720 | G57: =E57*J57 -> 0 | H57: ='RM Rollforward'!J82 -> 290 | I57: ='RM Rollforward'!L82 -> 52200 | K57: 46220 | M57: =D57-E57-L57 -> 70280 | N57: =E57+L57 -> 9720 | O57: =N57-D57 -> -70280
A58: R033 | B58: LDPE Inejction | C58: =if(E58<=350,"Critical",IF(E58<=750,"Low",IF(E58<=1250,"Moderate",IF(E58<=1500,"High")))) -> Moderate | D58: 0 | E58: ='RM Rollforward'!H36 -> 1200 | G58: =E58*J58 -> 0 | H58: ='RM Rollforward'!J37 -> 40 | I58: ='RM Rollforward'!L37 -> 2000 | K58: 0 | M58: =D58-E58-L58 -> -1200 | N58: =E58+L58 -> 1200 | O58: =N58-D58 -> 1200
A59: R034 | B59: Clarifying Agent (bags) | C59: =if(E59<=35,"Critical",IF(E59<=70,"Low",IF(E59<=140,"Moderate",IF(E59<=280,"High")))) -> Low | D59: 250 | E59: ='RM Rollforward'!H37 -> 50 | F59: 50 | G59: =E59*J59 -> 1500 | H59: ='RM Rollforward'!J9 -> 45 | I59: =SUM('RM Rollforward'!L9:L10) -> 954030 | J59: 30 | K59: 0 | M59: =D59-E59-L59 -> 200 | N59: =E59+L59 -> 50 | O59: =N59-D59 -> -200
A60: AC109 | B60: Paint Black | C60: =if(E60<=10,"Critical",IF(E60<=50,"Low",IF(E60<=150,"Moderate",IF(E60<200,"High")))) -> Moderate | D60: 0 | E60: ='RM Rollforward'!H77 -> 60 | K60: 0 | M60: =D60-E60-L60 -> -60 | N60: =E60+L60 -> 60 | O60: =N60-D60 -> 60
A61: AC113 | B61: Paint White | C61: =if(E61<=10,"Critical",IF(E61<=50,"Low",IF(E61<=150,"Moderate",IF(E61<200,"High")))) -> Moderate | D61: 0 | E61: ='RM Rollforward'!H81 -> 100 | K61: 0 | M61: =D61-E61-L61 -> -100 | N61: =E61+L61 -> 100 | O61: =N61-D61 -> 100
A62: AC117 | B62: Paint Orange | C62: =if(E62<=10,"Critical",IF(E62<=50,"Low",IF(E62<=150,"Moderate",IF(E62<200,"High")))) -> Moderate | D62: 0 | E62: ='RM Rollforward'!H85 -> 70 | K62: 0 | M62: =D62-E62-L62 -> -70 | N62: =E62+L62 -> 70 | O62: =N62-D62 -> 70

Sheet 0-3months
D2: High | E2: 0-3 Mons. | F2: Remaining PO | G2: Balance | H2: Incoming | I2: For Order
A3: AC021 | B3: Peanut Jar Cap 50mm (Small) | C3: Critical | D3: 720000 | E3: 2160000 | F3: 621000 | G3: 0 | H3: 292000 | I3: =E3-F3-G3 -> 1539000
A4: AC022 | B4: Peanut Jar Cap 67mm (Medium) | C4: Critical | D4: 480000 | E4: 1440000 | F4: 352800 | G4: 44800 | H4: 534000 | I4: =E4-F4-G4 -> 1042400
A5: AC107 | B5: Packaging Tape 1/2" | C5: Critical | D5: 0 | E5: 0 | F5: 1000 | G5: 354 | H5: 0 | I5: =E5-F5-G5 -> -1354
A6: R103 | B6: PET Bottle Pre-Formed 12g (30mm) | C6: Critical | D6: 900000 | E6: 2700000 | F6: 69000 | G6: 0 | H6: 30000 | I6: =E6-F6-G6 -> 2631000
A7: R105 | B7: PET Bottle Pre-Formed 22g (30mm) | C7: Critical | D7: 200000 | E7: 600000 | F7: 254400 | G7: 0 | H7: 0 | I7: =E7-F7-G7 -> 345600
A8: AC013 | B8: PET Bottle Cap White 30mm | C8: Critical | D8: 900000 | E8: 2700000 | F8: 360000 | G8: 0 | H8: 0 | I8: =E8-F8-G8 -> 2340000
A9: AC018 | B9: Gallon Cap | C9: Critical | D9: 0 | E9: 0 | F9: 0 | G9: 0 | H9: 0 | I9: =E9-F9-G9 -> 0
A10: AC004 | B10: Water Container Faucet | C10: Critical | D10: 40000 | E10: 120000 | F10: 60000 | G10: 7800 | H10: 20000 | I10: =E10-F10-G10 -> 52200
A11: AC005 | B11: Water Container Small Outer Cap | C11: High | D11: 80000 | E11: 240000 | F11: 0 | G11: 88500 | H11: 0 | I11: =E11-F11-G11 -> 151500
A12: AC106 | B12: Packaging Tape 2" | C12: Low | D12: 0 | E12: 0 | F12: 2000 | G12: 667 | H12: 0 | I12: =E12-F12-G12 -> -2667
A13: AC101 | B13: Plastic Twine | C13: Low | D13: 1200 | E13: 3600 | F13: 0 | G13: 498 | H13: 0 | I13: =E13-F13-G13 -> 3102
A14: AC008 | B14: Water Container Inner Cap | C14: Moderate | D14: 80000 | E14: 240000 | F14: 46220 | G14: 9720 | H14: 0 | I14: =E14-F14-G14 -> 184060
... A26: AC117 | B26: Paint Orange | C26: High | D26: 0 | E26: 0 | F26: 0 | G26: 70 | H26: 0 | I26: =E26-F26-G26 -> -70

Sheet ROLLS
B1: Rivson Goldplast Manufacturing Corp
B2: ROLLS
B3: ='RM Rollforward'!B3 -> As of June 20, 2025
A4: SKU Code | B4: SKU Description | C4: UOM | D4: Inventory | E4: Price | G4: Peso Value | H4: Remarks
A5: PPB501 | B5: PB-A2 Plastic Roll Mini Trans (Kgs) | C5: Kls | D5: ='RM Rollforward'!#REF! -> #ERROR! | E5: 75 | F5: 1 | G5: =D5*E5*F5 -> #ERROR!
A6: PPB502 | B6: PB-A2 Plastic Roll Mini White (Kgs) | C6: Kls | D6: ='RM Rollforward'!#REF! -> #ERROR! | E6: 75 | F6: 1 | G6: =D6*E6*F6 -> #ERROR!
A7: PPB503 | B7: PB-A2 Plastic Roll Tiny Trans (Kgs) | C7: Kls | D7: ='RM Rollforward'!#REF! -> #ERROR! | E7: 75 | F7: 1 | G7: =D7*E7*F7 -> #ERROR!
A8: PPB504 | B8: PB-A2 Plastic Roll Tiny White (Kgs) | C8: Kls | D8: ='RM Rollforward'!#REF! -> #ERROR! | E8: 75 | F8: 1 | G8: =D8*E8*F8 -> #ERROR!
A9: PPB505 | B9: PB-A2 Plastic Roll Medium Trans (Kgs) | C9: Kls | D9: ='RM Rollforward'!#REF! -> #ERROR! | E9: 75 | F9: 1 | G9: =D9*E9*F9 -> #ERROR!
A10: PPB506 | B10: PB-A2 Plastic Roll Medium White (Kgs) | C10: Kls | D10: 0 | E10: 75 | F10: 1 | G10: =D10*E10*F10 -> 0
A11: PPB507 | B11: PB-A2 Plastic Roll Large Trans (Kgs) | C11: Kls | D11: ='RM Rollforward'!#REF! -> #ERROR! | E11: 75 | F11: 1 | G11: =D11*E11*F11 -> #ERROR!
A12: PPB508 | B12: PB-A2 Plastic Roll Large White (Kgs) | C12: Kls | D12: ='RM Rollforward'!#REF! -> #ERROR! | E12: 75 | F12: 1 | G12: =D12*E12*F12 -> #ERROR!
A13: PPB551 | B13: PB-A Plastic Roll Mini Blue (Kgs) | C13: Kls | D13: ='RM Rollforward'!#REF! -> #ERROR! | E13: 75 | F13: 1 | G13: =D13*E13*F13 -> #ERROR!
A14: PPB552 | B14: PB-A Plastic Roll Mini Green (Kgs) | C14: Kls | D14: ='RM Rollforward'!#REF! -> #ERROR! | E14: 75 | F14: 1 | G14: =D14*E14*F14 -> #ERROR!
A15: PPB553 | B15: PB-A Plastic Roll Mini Orange (Kgs) | C15: Kls | D15: ='RM Rollforward'!#REF! -> #ERROR! | E15: 75 | F15: 1 | G15: =D15*E15*F15 -> #ERROR!
A16: PPB554 | B16: PB-A Plastic Roll Mini Red (Kgs) | C16: Kls | D16: ='RM Rollforward'!#REF! -> #ERROR! | E16: 75 | F16: 1 | G16: =D16*E16*F16 -> #ERROR!
A17: PPB555 | B17: PB-A Plastic Roll Mini Trans (Kgs) | C17: Kls | D17: ='RM Rollforward'!#REF! -> #ERROR! | E17: 75 | F17: 1 | G17: =D17*E17*F17 -> #ERROR!
A18: PPB556 | B18: PB-A Plastic Roll Mini White (Kgs) | C18: Kls | D18: ='RM Rollforward'!#REF! -> #ERROR! | E18: 75 | F18: 1 | G18: =D18*E18*F18 -> #ERROR!
A19: PPB557 | B19: PB-A Plastic Roll Mini Yellow (Kgs) | C19: Kls | D19: ='RM Rollforward'!#REF! -> #ERROR! | E19: 75 | F19: 1 | G19: =D19*E19*F19 -> #ERROR!
A20: PPB561 | B20: PB-A Plastic Roll Tiny Blue (Kgs) | C20: Kls | D20: ='RM Rollforward'!#REF! -> #ERROR! | E20: 75 | F20: 1 | G20: =D20*E20*F20 -> #ERROR!
A21: PPB562 | B21: PB-A Plastic Roll Tiny Green (Kgs) | C21: Kls | D21: ='RM Rollforward'!#REF! -> #ERROR! | E21: 75 | F21: 1 | G21: =D21*E21*F21 -> #ERROR!
A22: PPB563 | B22: PB-A Plastic Roll Tiny Orange (Kgs) | C22: Kls | D22: ='RM Rollforward'!#REF! -> #ERROR! | E22: 75 | F22: 1 | G22: =D22*E22*F22 -> #ERROR!
... A43: PPB593 | B43: PB-A Plastic Roll XLarge Orange (Kgs) | C43: Kls | D43: ='RM Rollforward'!#REF! -> #ERROR! | E43: 75 | F43: 1 | G43: =D43*E43*F43 -> #ERROR!
A44: PPB594 | B44: PB-A Plastic Roll XLarge Red (Kgs) | C44: Kls | D44: ='RM Rollforward'!#REF! -> #ERROR! | E44: 75 | F44: 1
A45: PPB595 | B45: PB-A Plastic Roll XLarge Trans (Kgs) | C45: Kls | D45: ='RM Rollforward'!#REF! -> #ERROR! | E45: 75 | F45: 1 | G45: =D45*E45*F45 -> #ERROR!
A46: PPB596 | B46: PB-A Plastic Roll XLarge White (Kgs) | C46: Kls | D46: ='RM Rollforward'!#REF! -> #ERROR! | E46: 75 | F46: 1 | G46: =D46*E46*F46 -> #ERROR!
A47: PPB597 | B47: PB-A Plastic Roll XLarge Yellow (Kgs) | C47: Kls | D47: ='RM Rollforward'!#REF! -> #ERROR! | E47: 75 | F47: 1 | G47: =D47*E47*F47 -> #ERROR!
A48: PPB351 | B48: PB-Roll Bag 100 5" (Kgs) | C48: Kls | D48: ='RM Rollforward'!#REF! -> #ERROR! | E48: 75 | F48: 1 | G48: =D48*E48*F48 -> #ERROR!
A49: PPB352 | B49: PB-Roll Bag 100 8" (Kgs) | C49: Kls | D49: ='RM Rollforward'!#REF! -> #ERROR! | E49: 75 | F49: 1 | G49: =D49*E49*F49 -> #ERROR!
A50: PPB353 | B50: PB-Roll Bag 100 10" (Kgs) | C50: Kls | D50: ='RM Rollforward'!#REF! -> #ERROR! | E50: 75 | F50: 1 | G50: =D50*E50*F50 -> #ERROR!
A51: PPB354 | B51: PB-Roll Bag 100 16" (Kgs) | C51: Kls | D51: ='RM Rollforward'!#REF! -> #ERROR! | E51: 75 | F51: 1 | G51: =D51*E51*F51 -> #ERROR!
A52: PPB355 | B52: PB-Roll Bag 100 20" (Kgs) | C52: Kls | D52: ='RM Rollforward'!#REF! -> #ERROR! | E52: 75 | F52: 1 | G52: =D52*E52*F52 -> #ERROR!
A53: PPB361 | B53: PB-Roll Bag 200 8" (Kgs) | C53: Kls | D53: ='RM Rollforward'!#REF! -> #ERROR! | E53: 75 | F53: 1 | G53: =D53*E53*F53 -> #ERROR!
A54: PPB362 | B54: PB-Roll Bag 200 10" (Kgs) | C54: Kls | D54: ='RM Rollforward'!#REF! -> #ERROR! | E54: 75 | F54: 1 | G54: =D54*E54*F54 -> #ERROR!
A55: PPB363 | B55: PB-Roll Bag 200 12" (Kgs) | C55: Kls | D55: ='RM Rollforward'!#REF! -> #ERROR! | E55: 75 | F55: 1 | G55: =D55*E55*F55 -> #ERROR!
A56: PPB364 | B56: PB-Roll Bag 200 16" (Kgs) | C56: Kls | D56: ='RM Rollforward'!#REF! -> #ERROR! | E56: 75 | F56: 1 | G56: =D56*E56*F56 -> #ERROR!
... A62: PPB605 | B62: PB-B Plastic Roll Mini White (Kgs) | C62: Kls | D62: ='RM Rollforward'!#REF! -> #ERROR! | E62: 43 | F62: 1 | G62: =D62*E62*F62 -> #ERROR!
A63: PPB606 | B63: PB-B Plastic Roll Tiny Black (Kgs) | C63: Kls | D63: ='RM Rollforward'!H550 -> 0 | E63: 43 | F63: 1 | G63: =D63*E63*F63 -> 0
A64: PPB607 | B64: PB-B Plastic Roll Tiny Blue (Kgs) | C64: Kls | D64: ='RM Rollforward'!H551 -> 363 | E64: 43 | F64: 1 | G64: =D64*E64*F64 -> 15609
A65: PPB608 | B65: PB-B Plastic Roll Tiny Green (Kgs) | C65: Kls | D65: ='RM Rollforward'!H552 -> 0 | E65: 43 | F65: 1 | G65: =D65*E65*F65 -> 0
A66: PPB609 | B66: PB-B Plastic Roll Tiny Red (Kgs) | C66: Kls | D66: ='RM Rollforward'!H553 -> 0 | E66: 43 | F66: 1 | G66: =D66*E66*F66 -> 0
A67: PPB610 | B67: PB-B Plastic Roll Tiny White (Kgs) | C67: Kls | D67: ='RM Rollforward'!H554 -> 0 | E67: 43 | F67: 1 | G67: =D67*E67*F67 -> 0
A68: PPB611 | B68: PB-B Plastic Roll Medium Black (Kgs) | C68: Kls | D68: ='RM Rollforward'!H566 -> 21 | E68: 43 | F68: 1 | G68: =D68*E68*F68 -> 903
A69: PPB612 | B69: PB-B Plastic Roll Medium Blue (Kgs) | C69: Kls | D69: ='RM Rollforward'!H567 -> 0 | E69: 43 | F69: 1 | G69: =D69*E69*F69 -> 0
A70: PPB613 | B70: PB-B Plastic Roll Medium Green (Kgs) | C70: Kls | D70: ='RM Rollforward'!H568 -> 110 | E70: 43 | F70: 1 | G70: =D70*E70*F70 -> 4730
A71: PPB614 | B71: PB-B Plastic Roll Medium Red (Kgs) | C71: Kls | D71: ='RM Rollforward'!H569 -> 0 | E71: 43 | F71: 1 | G71: =D71*E71*F71 -> 0
A72: PPB615 | B72: PB-B Plastic Roll Medium White (Kgs) | C72: Kls | D72: ='RM Rollforward'!H570 -> 0 | E72: 43 | F72: 1 | G72: =D72*E72*F72 -> 0
A73: PPB616 | B73: PB-B Plastic Roll Large Black (Kgs) | C73: Kls | D73: ='RM Rollforward'!H571 -> 0 | E73: 43 | F73: 1 | G73: =D73*E73*F73 -> 0
A74: PPB617 | B74: PB-B Plastic Roll Large Blue (Kgs) | C74: Kls | D74: ='RM Rollforward'!H572 -> 0 | E74: 43 | F74: 1 | G74: =D74*E74*F74 -> 0
A75: PPB618 | B75: PB-B Plastic Roll Large Green (Kgs) | C75: Kls | D75: ='RM Rollforward'!H573 -> 17 | E75: 43 | F75: 1 | G75: =D75*E75*F75 -> 731
A76: PPB619 | B76: PB-B Plastic Roll Large Red (Kgs) | C76: Kls | D76: ='RM Rollforward'!H574 -> 0 | E76: 43 | F76: 1 | G76: =D76*E76*F76 -> 0
A77: PPB620 | B77: PB-B Plastic Roll Large White (Kgs) | C77: Kls | D77: ='RM Rollforward'!H575 -> 0 | E77: 43 | F77: 1 | G77: =D77*E77*F77 -> 0
A78: PPB621 | B78: PB-B Plastic Roll XLarge Black (Kgs) | C78: Kls | D78: ='RM Rollforward'!H576 -> 0 | E78: 43 | F78: 1 | G78: =D78*E78*F78 -> 0
A79: PPB622 | B79: PB-B Plastic Roll XLarge Blue (Kgs) | C79: Kls | D79: ='RM Rollforward'!H577 -> 18 | E79: 43 | F79: 1 | G79: =D79*E79*F79 -> 774
... A171: PPB789 | B171: PB-A2 Plastic Roll Medium Orange (Kgs) | C171: Kls | D171: ='RM Rollforward'!H669 -> 356 | E171: 75 | F171: 1 | G171: =D171*E171*F171 -> 26700
A172: PPB790 | B172: PB-A2 Plastic Roll Medium Red (Kgs) | C172: Kls | D172: ='RM Rollforward'!H671 -> 0 | E172: 75 | F172: 1 | G172: =D172*E172*F172 -> 0
A173: PPB791 | B173: PB-A2 Plastic Roll Large Blue (Kgs) | C173: Kls | D173: ='RM Rollforward'!H672 -> 0 | E173: 75 | F173: 1 | G173: =D173*E173*F173 -> 0
A174: PPB792 | B174: PB-A2 Plastic Roll Large Orange (Kgs) | C174: Kls | D174: ='RM Rollforward'!H673 -> 0 | E174: 75 | F174: 1 | G174: =D174*E174*F174 -> 0
A175: PPB793 | B175: PB-A2 Plastic Roll Large Red (Kgs) | C175: Kls | D175: ='RM Rollforward'!H674 -> 0 | E175: 75 | F175: 1 | G175: =D175*E175*F175 -> 0
A176: PPB794 | B176: PB-D Plastic Roll Mini Yellow (Kgs) | C176: Kls | D176: ='RM Rollforward'!#REF! -> #ERROR! | E176: 43 | F176: 1 | G176: =D176*E176*F176 -> #ERROR!
A177: PPB795 | B177: PB-D Plastic Roll Tiny Yellow (Kgs) | C177: Kls | D177: ='RM Rollforward'!#REF! -> #ERROR! | E177: 43 | F177: 1 | G177: =D177*E177*F177 -> #ERROR!
A178: PPB796 | B178: PB-D Plastic Roll Medium Yellow (Kgs) | C178: Kls | D178: ='RM Rollforward'!#REF! -> #ERROR! | E178: 43 | F178: 1 | G178: =D178*E178*F178 -> #ERROR!
A179: PPB797 | B179: PB-D Plastic Roll Large Yellow (Kgs) | C179: Kls | D179: ='RM Rollforward'!#REF! -> #ERROR! | E179: 43 | F179: 1 | G179: =D179*E179*F179 -> #ERROR!
A180: PPB798 | B180: PB-F Plastic Roll Mini White (Kgs) | C180: Kls | D180: ='RM Rollforward'!#REF! -> #ERROR! | E180: 43 | F180: 1 | G180: =D180*E180*F180 -> #ERROR!
A181: PPB799 | B181: PB-F Plastic Roll Tiny White (Kgs) | C181: Kls | D181: ='RM Rollforward'!#REF! -> #ERROR! | E181: 43 | F181: 1 | G181: =D181*E181*F181 -> #ERROR!
A182: PPB800 | B182: PB-F Plastic Roll Medium White (Kgs) | C182: Kls | D182: ='RM Rollforward'!#REF! -> #ERROR! | E182: 43 | F182: 1 | G182: =D182*E182*F182 -> #ERROR!
A183: PPB801 | B183: PB-F Plastic Roll Large White (Kgs) | C183: Kls | D183: ='RM Rollforward'!#REF! -> #ERROR! | E183: 43 | F183: 1 | G183: =D183*E183*F183 -> #ERROR!
A184: PPB802 | B184: PB-A2 Plastic Roll Mini Green (Kgs) | C184: Kls | D184: ='RM Rollforward'!#REF! -> #ERROR! | E184: 75 | F184: 1 | G184: =D184*E184*F184 -> #ERROR!
A185: PPB803 | B185: PB-A2 Plastic Roll Tiny Green (Kgs) | C185: Kls | D185: ='RM Rollforward'!#REF! -> #ERROR! | E185: 75 | F185: 1 | G185: =D185*E185*F185 -> #ERROR!
A186: PPB804 | B186: PB-A2 Plastic Roll Medium Green (Kgs) | C186: Kls | D186: ='RM Rollforward'!#REF! -> #ERROR! | E186: 75 | F186: 1 | G186: =D186*E186*F186 -> #ERROR!
A187: PPB805 | B187: PB-A2 Plastic Roll Large Green (Kgs) | C187: Kls | D187: ='RM Rollforward'!#REF! -> #ERROR! | E187: 75 | F187: 1 | G187: =D187*E187*F187 -> #ERROR!
A188: PPB806 | B188: PB-B Plastic Roll Large Yellow (Kgs) | C188: Kls | D188: ='RM Rollforward'!#REF! -> #ERROR! | E188: 43 | F188: 1 | G188: =D188*E188*F188 -> #ERROR!
A189: PPB807 | B189: PB-B Plastic Roll MIni Yellow (Kgs) | C189: Kls | D189: ='RM Rollforward'!#REF! -> #ERROR! | E189: 43 | G189: =D189*E189*F189 -> #ERROR!
D190: =SUM(D5:D189) -> #ERROR! | G190: =SUM(G5:G189) -> #ERROR!

Sheet PACKAGING
B1: Rivson Goldplast Manufacturing Corp
B2: PACKAGING
B3: ='RM Rollforward'!B3 -> As of June 20, 2025
A4: SKU Code | B4: SKU Description | C4: UOM | D4: Inventory | E4: Price | G4: Peso Value | H4: Remarks
A5: PPR201 | B5: PR-Roll PB Aloha Mini (Kgs) | C5: Kls | D5: ='RM Rollforward'!H122 -> 348 | E5: 5 | F5: 1 | G5: =D5*E5*F5 -> 1740
A6: PPR202 | B6: PR-Roll PB Aloha Tiny (Kgs) | C6: Kls | D6: ='RM Rollforward'!H123 -> 82 | E6: 5 | F6: 1 | G6: =D6*E6*F6 -> 410
A7: PPR203 | B7: PR-Roll PB Aloha Medium (Kgs) | C7: Kls | D7: ='RM Rollforward'!H124 -> 27 | E7: 5 | F7: 1 | G7: =D7*E7*F7 -> 135
A8: PPR204 | B8: PR-Roll PB Aloha Large (Kgs) | C8: Kls | D8: ='RM Rollforward'!H125 -> 252 | E8: 5 | F8: 1 | G8: =D8*E8*F8 -> 1260
A9: PPR205 | B9: PP-Roll PB Boston Mini Black (Kgs) | C9: Kls | D9: ='RM Rollforward'!H126 -> 132 | E9: 5 | F9: 1 | G9: =D9*E9*F9 -> 660
A10: PPR206 | B10: PP-Roll PB Boston Tiny Black (Kgs) | C10: Kls | D10: ='RM Rollforward'!H127 -> 0 | E10: 5 | F10: 1 | G10: =D10*E10*F10 -> 0
A11: PPR207 | B11: PP-Roll PB Boston Medium Black (Kgs) | C11: Kls | D11: ='RM Rollforward'!H128 -> 56 | E11: 5 | F11: 1 | G11: =D11*E11*F11 -> 280
A12: PPR208 | B12: PP-Roll PB Boston Large Black (Kgs) | C12: Kls | D12: ='RM Rollforward'!H129 -> 0 | E12: 5 | F12: 1 | G12: =D12*E12*F12 -> 0
A13: PPR209 | B13: PP-Roll PB Boston Mini Green (Kgs) | C13: Kls | D13: ='RM Rollforward'!H130 -> 0 | E13: 5 | F13: 1 | G13: =D13*E13*F13 -> 0
A14: PPR210 | B14: PP-Roll PB Boston Tiny Green (Kgs) | C14: Kls | D14: ='RM Rollforward'!H131 -> 0 | E14: 5 | F14: 1 | G14: =D14*E14*F14 -> 0
A15: PPR211 | B15: PP-Roll PB Boston Medium Green (Kgs) | C15: Kls | D15: ='RM Rollforward'!H132 -> 178 | E15: 5 | F15: 1 | G15: =D15*E15*F15 -> 890
A16: PPR212 | B16: PP-Roll PB Boston Large Green (Kgs) | C16: Kls | D16: ='RM Rollforward'!H133 -> 0 | E16: 5 | F16: 1 | G16: =D16*E16*F16 -> 0
... A126: PPR323 | B126: PP-Roll PB Pitbull Large (Kgs) | C126: Kls | D126: ='RM Rollforward'!H243 -> 42 | E126: 5 | F126: 1 | G126: =D126*E126*F126 -> 210
A127: PPB459 | B127: PP-Roll Spring 6X10 (Kgs) | C127: Kls | D127: ='RM Rollforward'!H257 -> 0 | E127: 5 | F127: 1 | G127: =D127*E127*F127 -> 0
A128: PPB460 | B128: PP-Roll Spring 7X10 (Kgs) | C128: Kls | D128: ='RM Rollforward'!H258 -> 0 | E128: 5 | F128: 1 | G128: =D128*E128*F128 -> 0
A129: PPB461 | B129: PP-Roll Spring 5X10 (Kgs) | C129: Kls | D129: ='RM Rollforward'!H259 -> 71 | E129: 5 | F129: 1 | G129: =D129*E129*F129 -> 355
A130: PPB462 | B130: PP-Roll Spring 6 1/2 X10 (Kgs) | C130: Kls | D130: ='RM Rollforward'!H260 -> 0 | E130: 5 | F130: 1 | G130: =D130*E130*F130 -> 0
A131: PPB465 | B131: PP-Roll Swerte 10x13 (Kgs) | C131: Kls | D131: ='RM Rollforward'!H262 -> 78 | E131: 5 | F131: 1 | G131: =D131*E131*F131 -> 390
A132: PPB466 | B132: PP-Roll Swerte 5x5 (Kgs) | C132: Kls | D132: ='RM Rollforward'!H263 -> 222 | E132: 5 | F132: 1 | G132: =D132*E132*F132 -> 1110
A133: PPB467 | B133: PP-Roll Swerte 9x9 (Kgs) | C133: Kls | D133: ='RM Rollforward'!H264 -> -2 | E133: 5 | F133: 1 | G133: =D133*E133*F133 -> -10
A134: PPR551 | B134: PP-Roll ST Greatwall (Kgs) | C134: Kls | D134: ='RM Rollforward'!H265 -> 0 | E134: 5 | F134: 1 | G134: =D134*E134*F134 -> 0
A135: PPR552 | B135: PR-Roll ST Aloha Jumbo (Kgs) | C135: Kls | D135: ='RM Rollforward'!H266 -> 0 | E135: 5 | F135: 1 | G135: =D135*E135*F135 -> 0
A136: PPR553 | B136: PP-Roll ST ALoha King (Kgs) | C136: Kls | D136: ='RM Rollforward'!H267 -> 0 | E136: 5 | F136: 1 | G136: =D136*E136*F136 -> 0
A137: PPR554 | B137: PR-Roll ST Liberty King (Kgs) | C137: Kls | D137: ='RM Rollforward'!H268 -> 0 | E137: 5 | F137: 1 | G137: =D137*E137*F137 -> 0
A138: PPR555 | B138: PP-Roll ST Lucky (Kgs) | C138: Kls | D138: ='RM Rollforward'!H269 -> 0 | E138: 5 | F138: 1 | G138: =D138*E138*F138 -> 0
A139: PPR556 | B139: PP-Roll ST Liwanag (Kgs) | C139: Kls | D139: ='RM Rollforward'!H270 -> 94 | E139: 5 | F139: 1 | G139: =D139*E139*F139 -> 470
A140: PPR651 | B140: PR-Roll Disposable Cups 3oz | C140: Kls | D140: ='RM Rollforward'!H271 -> 118 | E140: 5 | F140: 1 | G140: =D140*E140*F140 -> 590
A141: PPR652 | B141: PR-Roll Disposable Cups 5oz | C141: Kls | D141: ='RM Rollforward'!H272 -> 160 | E141: 5 | F141: 1 | G141: =D141*E141*F141 -> 800
A142: PPR653 | B142: PR-Roll Disposable Cups 6oz | C142: Kls | D142: ='RM Rollforward'!H273 -> 114 | E142: 5 | F142: 1 | G142: =D142*E142*F142 -> 570
... A147: PPR658 | B147: PR-Roll Disposable Cups 16oz | C147: Kls | D147: ='RM Rollforward'!H278 -> 0 | E147: 5 | F147: 1 | G147: =D147*E147*F147 -> 0
A148: PPR001 | B148: PR-Packaging PB Aloha Mini (Pcs) | C148: Pcs | D148: ='RM Rollforward'!H301 -> 59 | E148: 0.25 | F148: 500 | G148: =D148*E148*F148 -> 7375
A149: PPR002 | B149: PR-Packaging PB Aloha Tiny (Pcs) | C149: Pcs | D149: ='RM Rollforward'!H302 -> 20 | E149: 0.25 | F149: 500 | G149: =D149*E149*F149 -> 2500
A150: PPR003 | B150: PR-Packaging PB Aloha Medium (Pcs) | C150: Pcs | D150: ='RM Rollforward'!H303 -> 3 | E150: 0.25 | F150: 500 | G150: =D150*E150*F150 -> 375
A151: PPR004 | B151: PR-Packaging PB Aloha Large (Pcs) | C151: Pcs | D151: ='RM Rollforward'!H304 -> 0 | E151: 0.25 | F151: 500 | G151: =D151*E151*F151 -> 0
A152: PPR005 | B152: PR-Packaging PB Boston Mini Black (Pcs) | C152: Pcs | D152: ='RM Rollforward'!H305 -> 0 | E152: 0.25 | F152: 500 | G152: =D152*E152*F152 -> 0
A153: PPR006 | B153: PR-Packaging PB Boston Tiny Black (Pcs) | C153: Pcs | D153: ='RM Rollforward'!H306 -> 20 | E153: 0.25 | F153: 500 | G153: =D153*E153*F153 -> 2500
A154: PPR007 | B154: PR-Packaging PB Boston Medium Black (Pcs) | C154: Pcs | D154: ='RM Rollforward'!H307 -> 0 | E154: 0.25 | F154: 500 | G154: =D154*E154*F154 -> 0
A155: PPR008 | B155: PR-Packaging PB Boston Large Black (Pcs) | C155: Pcs | D155: ='RM Rollforward'!H308 -> 0 | E155: 0.25 | F155: 500 | G155: =D155*E155*F155 -> 0
A156: PPR009 | B156: PR-Packaging PB Boston Mini Green (Pcs) | C156: Pcs | D156: ='RM Rollforward'!H309 -> 0 | E156: 0.25 | F156: 500 | G156: =D156*E156*F156 -> 0
A157: PPR010 | B157: PR-Packaging PB Boston Tiny Green (Pcs) | C157: Pcs | D157: ='RM Rollforward'!H310 -> 0 | E157: 0.25 | F157: 500 | G157: =D157*E157*F157 -> 0
A158: PPR011 | B158: PR-Packaging PB Boston Medium Green (Pcs) | C158: Pcs | D158: ='RM Rollforward'!H311 -> 0 | E158: 0.25 | F158: 500 | G158: =D158*E158*F158 -> 0
A159: PPR012 | B159: PR-Packaging PB Boston Large Green (Pcs) | C159: Pcs | D159: ='RM Rollforward'!H312 -> 0 | E159: 0.25 | F159: 500 | G159: =D159*E159*F159 -> 0
... A269: PPR123 | B269: PR-Packaging PB Pitbull Large (Pcs) | C269: Pcs | D269: ='RM Rollforward'!H422 -> 0 | E269: 0.25 | F269: 500 | G269: =D269*E269*F269 -> 0
A270: PPR701 | B270: PR-Packaging Spring 5x8 (500s) | C270: Pcs | D270: ='RM Rollforward'!H435 -> 0 | E270: 0.25 | F270: 500 | G270: =D270*E270*F270 -> 0
A271: PPR702 | B271: PR-Packaging Spring 5x10 (500s) | C271: Pcs | D271: ='RM Rollforward'!H436 -> 17 | E271: 0.25 | F271: 500 | G271: =D271*E271*F271 -> 2125
A272: PPR703 | B272: PR-Packaging Spring 6x10 (500s) | C272: Pcs | D272: ='RM Rollforward'!H437 -> 10 | E272: 0.25 | F272: 500 | G272: =D272*E272*F272 -> 1250
A273: PPR704 | B273: PR-Packaging Spring 6x12 (500s) | C273: Pcs | D273: ='RM Rollforward'!H438 -> 0 | E273: 0.25 | F273: 500 | G273: =D273*E273*F273 -> 0
A274: PPR705 | B274: PR-Packaging Spring 6x14 (500s) | C274: Pcs | D274: ='RM Rollforward'!H439 -> 0 | E274: 0.25 | F274: 500 | G274: =D274*E274*F274 -> 0
A275: PPR706 | B275: PR-Packaging Spring 7x12 (500s) | C275: Pcs | D275: ='RM Rollforward'!H440 -> 0 | E275: 0.25 | F275: 500 | G275: =D275*E275*F275 -> 0
A276: PPR707 | B276: PR-Packaging Spring 7x14 (500s) | C276: Pcs | D276: ='RM Rollforward'!H441 -> 0 | E276: 0.25 | F276: 500 | G276: =D276*E276*F276 -> 0
A277: PPR708 | B277: PR-Packaging Spring 8x16 (500s) | C277: Pcs | D277: ='RM Rollforward'!H442 -> 9 | E277: 0.25 | F277: 500 | G277: =D277*E277*F277 -> 1125
A278: PPR709 | B278: PR-Packaging Spring 6 1/2 (500s) | C278: Pcs | D278: ='RM Rollforward'!H443 -> 0 | E278: 0.25 | F278: 500 | G278: =D278*E278*F278 -> 0
A279: PPR710 | B279: PR-Packaging Spring 7 1/2 (500s) | C279: Pcs | D279: ='RM Rollforward'!H444 -> 0 | E279: 0.25 | F279: 500 | G279: =D279*E279*F279 -> 0
A280: PPR711 | B280: PR-Packaging Spring 5 1/2 (500s) | C280: Pcs | D280: ='RM Rollforward'!H445 -> 0 | E280: 0.25 | F280: 500 | G280: =D280*E280*F280 -> 0
A281: PPR712 | B281: PR-Packaging Spring 7x10 (500s) | C281: Pcs | D281: ='RM Rollforward'!H446 -> 0 | E281: 0.25 | F281: 500 | G281: =D281*E281*F281 -> 0
... A283: PPR714 | B283: PR-Packaging Swerte 9x9 | C283: Pcs | D283: ='RM Rollforward'!H448 -> 0 | E283: 0.25 | F283: 500 | G283: =D283*E283*F283 -> 0
A284: PPR801 | B284: PP-Packaging Plain 7X12 (Pcs) | C284: Pcs | D284: ='RM Rollforward'!H450 -> 1 | E284: 0.25 | F284: 500 | G284: =D284*E284*F284 -> 125
A285: PPR802 | B285: PP-Packaging Plain 8X12 (Pcs) | C285: Pcs | D285: ='RM Rollforward'!H451 -> 0 | E285: 0.25 | F285: 500 | G285: =D285*E285*F285 -> 0
A286: PPR803 | B286: PP-Packaging Plain 8X16 (Pcs) | C286: Pcs | D286: ='RM Rollforward'!H452 -> 25 | E286: 0.25 | F286: 500 | G286: =D286*E286*F286 -> 3125
A287: PPR804 | B287: PP-Packaging Plain 8X17 (Pcs) | C287: Pcs | D287: ='RM Rollforward'!H453 -> 17 | E287: 0.25 | F287: 500 | G287: =D287*E287*F287 -> 2125
A288: PPR805 | B288: PP-Packaging Plain 9X18 (Pcs) | C288: Pcs | D288: ='RM Rollforward'!H454 -> 15 | E288: 0.25 | F288: 500 | G288: =D288*E288*F288 -> 1875
A289: PPR806 | B289: PP-Packaging Plain 9X19 (Pcs) | C289: Pcs | D289: ='RM Rollforward'!H455 -> 0 | E289: 0.25 | F289: 500 | G289: =D289*E289*F289 -> 0
A290: PPR501 | B290: PR-Packaging ST Greatwall (Pcs) | C290: Pcs | D290: ='RM Rollforward'!H509 -> 312 | E290: 0.25 | F290: 500 | G290: =D290*E290*F290 -> 39000
A291: PPR502 | B291: PR-Packaging ST Aloha Jumbo (Pcs) | C291: Pcs | D291: ='RM Rollforward'!H510 -> 63 | E291: 0.25 | F291: 500 | G291: =D291*E291*F291 -> 7875
A292: PPR503 | B292: PR-Packaging ST Aloha King (Pcs) | C292: Pcs | D292: ='RM Rollforward'!H511 -> 0 | E292: 0.25 | F292: 500 | G292: =D292*E292*F292 -> 0
A293: PPR504 | B293: PR-Packaging ST Liberty King (Pcs) | C293: Pcs | D293: ='RM Rollforward'!H512 -> 0 | E293: 0.25 | F293: 500 | G293: =D293*E293*F293 -> 0
A294: PPR505 | B294: PR-Packaging ST Lucky (Pcs) | C294: Pcs | D294: ='RM Rollforward'!H513 -> 0 | E294: 0.25 | F294: 500 | G294: =D294*E294*F294 -> 0
A295: PPR506 | B295: PR-Packaging ST Liwanag (Pcs) | C295: Pcs | D295: ='RM Rollforward'!H514 -> 0 | E295: 0.25 | F295: 500 | G295: =D295*E295*F295 -> 0
A296: PPR601 | B296: PR-Packaging Disposable Cups 3oz | C296: Pcs | D296: ='RM Rollforward'!H515 -> 2798 | E296: 0.25 | F296: 500 | G296: =D296*E296*F296 -> 349750
A297: PPR602 | B297: PR-Packaging Disposable Cups 5oz | C297: Pcs | D297: ='RM Rollforward'!H516 -> 390 | E297: 0.25 | F297: 500 | G297: =D297*E297*F297 -> 48750
A298: PPR603 | B298: PR-Packaging Disposable Cups 6oz | C298: Pcs | D298: ='RM Rollforward'!H517 -> 422 | E298: 0.25 | F298: 500 | G298: =D298*E298*F298 -> 52750
A299: PPR604 | B299: PR-Packaging Disposable Cups 7oz | C299: Pcs | D299: ='RM Rollforward'!H518 -> 3687 | E299: 0.25 | F299: 500 | G299: =D299*E299*F299 -> 460875
A300: PPR605 | B300: PR-Packaging Disposable Cups 8oz | C300: Pcs | D300: ='RM Rollforward'!H519 -> 867 | E300: 0.25 | F300: 500 | G300: =D300*E300*F300 -> 108375
A301: PPR606 | B301: PR-Packaging Disposable Cups 10oz | C301: Pcs | D301: ='RM Rollforward'!H520 -> 0 | E301: 0.25 | F301: 500 | G301: =D301*E301*F301 -> 0
... A303: PPR608 | B303: PR-Packaging Disposable Cups 16oz | C303: Pcs | D303: ='RM Rollforward'!H522 -> 0 | E303: 0.25 | F303: 500 | G303: =D303*E303*F303 -> 0
G304: =SUM(G5:G303) -> 1358130

Sheet Sacks
C2: Rivson Goldplast Manufacturing Corp
A5: Date | B5: Ldpe Sack | C5: Out | D5: Balance | E5: PP Sack | F5: Out | G5: Balance | H5: Green Sack | I5: Out | J5: Balance
A6: Sept 01 | B6: =3280+1250 -> 4530 | C6: 20 | D6: =B6-C6 -> 4510 | E6: 403 | G6: =E6-F6 -> 403 | H6: 1967 | I6: =50+40 -> 90 | J6: =H6-I6 -> 1877
A7: Sept 02 | D7: =D6+B7-C7 -> 4510 | G7: =G6+E7-F7 -> 403 | I7: 75 | J7: =J6+H7-I7 -> 1802
A8: Sept 03 | D8: =D7+B8-C8 -> 4510 | G8: =G7+E8-F8 -> 403 | J8: =J7+H8-I8 -> 1802
A9: Sept 04 | C9: 20 | D9: =D8+B9-C9 -> 4490 | F9: 60 | G9: =G8+E9-F9 -> 343 | I9: =70+60+80 -> 210 | J9: =J8+H9-I9 -> 1592
A10: Sept 05 | C10: 20 | D10: =D9+B10-C10 -> 4470 | G10: =G9+E10-F10 -> 343 | I10: 60 | J10: =J9+H10-I10 -> 1532
A11: Sept 06 | C11: 20 | D11: =D10+B11-C11 -> 4450 | G11: =G10+E11-F11 -> 343 | I11: 10 | J11: =J10+H11-I11 -> 1522
A12: Sept 07 | D12: =D11+B12-C12 -> 4450 | G12: =G11+E12-F12 -> 343 | I12: 20 | J12: =J11+H12-I12 -> 1502
A13: Sept 08 | D13: =D12+B13-C13 -> 4450 | G13: =G12+E13-F13 -> 343 | I13: 40 | J13: =J12+H13-I13 -> 1462
A14: Sept 09 | D14: =D13+B14-C14 -> 4450 | G14: =G13+E14-F14 -> 343 | J14: =J13+H14-I14 -> 1462
A15: Sept 10 | D15: =D14+B15-C15 -> 4450 | G15: =G14+E15-F15 -> 343 | I15: 40 | J15: =J14+H15-I15 -> 1422
A16: Sept 11 | C16: 20 | D16: =D15+B16-C16 -> 4430 | G16: =G15+E16-F16 -> 343 | I16: 40 | J16: =J15+H16-I16 -> 1382
A17: Sept 12 | C17: 20 | D17: =D16+B17-C17 -> 4410 | G17: =G16+E17-F17 -> 343 | J17: =J16+H17-I17 -> 1382
A18: Sept 13 | D18: =D17+B18-C18 -> 4410 | G18: =G17+E18-F18 -> 343 | J18: =J17+H18-I18 -> 1382
A19: Sept 14 | C19: 20 | D19: =D18+B19-C19 -> 4390 | G19: =G18+E19-F19 -> 343 | I19: 20 | J19: =J18+H19-I19 -> 1362
A20: Sept 15 | D20: =D19+B20-C20 -> 4390 | G20: =G19+E20-F20 -> 343 | I20: =30+30+24 -> 84 | J20: =J19+H20-I20 -> 1278
A21: Sept 16 | C21: 20 | D21: =D20+B21-C21 -> 4370 | G21: =G20+E21-F21 -> 343 | J21: =J20+H21-I21 -> 1278
A22: Sept 17 | D22: =D21+B22-C22 -> 4370 | F22: 100 | G22: =G21+E22-F22 -> 243 | I22: =30+40 -> 70 | J22: =J21+H22-I22 -> 1208
A23: Sept 18 | C23: 40 | D23: =D22+B23-C23 -> 4330 | G23: =G22+E23-F23 -> 243 | J23: =J22+H23-I23 -> 1208
A24: Sept 19 | C24: 20 | D24: =D23+B24-C24 -> 4310 | G24: =G23+E24-F24 -> 243 | I24: =100+43 -> 143 | J24: =J23+H24-I24 -> 1065
A25: Sept 20 | D25: =D24+B25-C25 -> 4310 | G25: =G24+E25-F25 -> 243 | I25: =20+20 -> 40 | J25: =J24+H25-I25 -> 1025
A26: Sept 21 | C26: 20 | D26: =D25+B26-C26 -> 4290 | G26: =G25+E26-F26 -> 243 | I26: =40+40 -> 80 | J26: =J25+H26-I26 -> 945
A27: Sept 22 | D27: =D26+B27-C27 -> 4290 | G27: =G26+E27-F27 -> 243 | I27: 60 | J27: =J26+H27-I27 -> 885
A28: Sept 23 | C28: 20 | D28: =D27+B28-C28 -> 4270 | G28: =G27+E28-F28 -> 243 | I28: =40+40+20+60+30 -> 190 | J28: =J27+H28-I28 -> 695
A29: Sept 24 | D29: =D28+B29-C29 -> 4270 | G29: =G28+E29-F29 -> 243 | I29: 40 | J29: =J28+H29-I29 -> 655
A30: Sept 25 | C30: 20 | D30: =D29+B30-C30 -> 4250 | G30: =G29+E30-F30 -> 243 | I30: =100+20 -> 120 | J30: =J29+H30-I30 -> 535
A31: Sept 26 | D31: =D30+B31-C31 -> 4250 | G31: =G30+E31-F31 -> 243 | J31: =J30+H31-I31 -> 535
A32: Sept 27 | D32: =D31+B32-C32 -> 4250 | G32: =G31+E32-F32 -> 243 | J32: =J31+H32-I32 -> 535
A33: Sept 28 | D33: =D32+B33-C33 -> 4250 | G33: =G32+E33-F33 -> 243 | J33: =J32+H33-I33 -> 535
A34: Sept 29 | D34: =D33+B34-C34 -> 4250 | G34: =G33+E34-F34 -> 243 | J34: =J33+H34-I34 -> 535
A35: Sept 30 | D35: =D34+B35-C35 -> 4250 | G35: =G34+E35-F35 -> 243 | J35: =J34+H35-I35 -> 535
